signext/signext.sv
//signext.sv

/* I was tempted to change raw_src to [39:0] but that may cause problems
with ease of emulation since C compilers can't handle 40-bits directly (probably have to use a 64-bit integer)
and also because it would be the only thing in the entire design that isn't an 8, 16, 32, or
64-bit number. As you can see those are all "standard" widths.

There may also be problems with programmers wishing they could do 40-bit jumps with branches.
They'd ask "why can I do a 40-bit unconditional but not a 40-bit branch?"
The target of my ISA is a beginner and beginners ask these type of questions.

But more importantly it affects THE REST of the design. cpu.sv and alu.sv would have to be aware
of this as well. People may want to load 40-bit immediates somehow to do a jump and they'd waste
two instructions to do that (an upper 8-bit load immediate and a lower 32-bit load immediate). */

module signext (
    //IN
    input logic [31:0] raw_src,
    input logic [2:0] imm_source,
    //OUT (immediate)
    output logic [63:0] immediate
    );

   // logic [31:0] gathered_imm;

    always_comb begin
        case(imm_source)
            // For I-Types
            3'b000: immediate = {{32{raw_src[31]}}, raw_src};
            // For S-types
            3'b001: immediate = {{32{raw_src[31]}}, raw_src};
            // For B-types
            3'b010: immediate = {{32{raw_src[31]}}, raw_src};
            // For J-types (Yeah guess what? Same thing again haha!)
            3'b011: immediate = {{32{raw_src[31]}}, raw_src};
            // U-types are actually different for once
            3'b100: immediate = {raw_src, 32'h00000000};
            default: immediate = 64'b0;
        endcase
    end

    // assign immediate = {{32{raw_src[31]}}, raw_src};

endmodule

signext/dump.vcd
$version Generated by VerilatedVcd $end
$timescale 1ps $end
 $scope module $rootio $end
  $var wire 32 # raw_src [31:0] $end
  $var wire 3 $ imm_source [2:0] $end
  $var wire 64 % immediate [63:0] $end
 $upscope $end
 $scope module signext $end
  $var wire 32 ' raw_src [31:0] $end
  $var wire 3 ( imm_source [2:0] $end
  $var wire 64 ) immediate [63:0] $end
 $upscope $end
$enddefinitions $end


#0
b00000000000000000000000000000000 #
b000 $
b0000000000000000000000000000000000000000000000000000000000000000 %
b00000000000000000000000000000000 '
b000 (
b0000000000000000000000000000000000000000000000000000000000000000 )
#1000
b00001101010111011110010110010011 #
b0000000000000000000000000000000000001101010111011110010110010011 %
b00001101010111011110010110010011 '
b0000000000000000000000000000000000001101010111011110010110010011 )
#3001
b11111111111111111111111111010110 #
b1111111111111111111111111111111111111111111111111111111111010110 %
b11111111111111111111111111010110 '
b1111111111111111111111111111111111111111111111111111111111010110 )
#104002
b00011001101001010110100011110111 #
b001 $
b0000000000000000000000000000000000011001101001010110100011110111 %
b00011001101001010110100011110111 '
b001 (
b0000000000000000000000000000000000011001101001010110100011110111 )
#105002
b10100010000110101010101000100101 #
b1111111111111111111111111111111110100010000110101010101000100101 %
b10100010000110101010101000100101 '
b1111111111111111111111111111111110100010000110101010101000100101 )
#206002
b00101001111101111101011110000000 #
b0000000000000000000000000000000000101001111101111101011110000000 %
b00101001111101111101011110000000 '
b0000000000000000000000000000000000101001111101111101011110000000 )
#207002
b10011011111110011110000010011111 #
b1111111111111111111111111111111110011011111110011110000010011111 %
b10011011111110011110000010011111 '
b1111111111111111111111111111111110011011111110011110000010011111 )
#308002
b00100001011000000100101111101101 #
b0000000000000000000000000000000000100001011000000100101111101101 %
b00100001011000000100101111101101 '
b0000000000000000000000000000000000100001011000000100101111101101 )
#309002
b11111111010010110100110110111010 #
b1111111111111111111111111111111111111111010010110100110110111010 %
b11111111010010110100110110111010 '
b1111111111111111111111111111111111111111010010110100110110111010 )
#410002
b00000010111110101010100011100010 #
b0000000000000000000000000000000000000010111110101010100011100010 %
b00000010111110101010100011100010 '
b0000000000000000000000000000000000000010111110101010100011100010 )
#411002
b11101100100110000000111001010101 #
b1111111111111111111111111111111111101100100110000000111001010101 %
b11101100100110000000111001010101 '
b1111111111111111111111111111111111101100100110000000111001010101 )
#512002
b01111011110110011001101011011010 #
b0000000000000000000000000000000001111011110110011001101011011010 %
b01111011110110011001101011011010 '
b0000000000000000000000000000000001111011110110011001101011011010 )
#513002
b11000011111111101100100111101111 #
b1111111111111111111111111111111111000011111111101100100111101111 %
b11000011111111101100100111101111 '
b1111111111111111111111111111111111000011111111101100100111101111 )
#614002
b00110000000001000000001101110011 #
b0000000000000000000000000000000000110000000001000000001101110011 %
b00110000000001000000001101110011 '
b0000000000000000000000000000000000110000000001000000001101110011 )
#615002
b10001111110100111101011000010101 #
b1111111111111111111111111111111110001111110100111101011000010101 %
b10001111110100111101011000010101 '
b1111111111111111111111111111111110001111110100111101011000010101 )
#716002
b00100000110110001011111011010111 #
b0000000000000000000000000000000000100000110110001011111011010111 %
b00100000110110001011111011010111 '
b0000000000000000000000000000000000100000110110001011111011010111 )
#717002
b11100001111100010110010011100111 #
b1111111111111111111111111111111111100001111100010110010011100111 %
b11100001111100010110010011100111 '
b1111111111111111111111111111111111100001111100010110010011100111 )
#818002
b01110101111001110110111101101000 #
b0000000000000000000000000000000001110101111001110110111101101000 %
b01110101111001110110111101101000 '
b0000000000000000000000000000000001110101111001110110111101101000 )
#819002
b10010010011011111010000101001101 #
b1111111111111111111111111111111110010010011011111010000101001101 %
b10010010011011111010000101001101 '
b1111111111111111111111111111111110010010011011111010000101001101 )
#920002
b00000100111010001000000100101101 #
b0000000000000000000000000000000000000100111010001000000100101101 %
b00000100111010001000000100101101 '
b0000000000000000000000000000000000000100111010001000000100101101 )
#921002
b11110111111001111100001000000101 #
b1111111111111111111111111111111111110111111001111100001000000101 %
b11110111111001111100001000000101 '
b1111111111111111111111111111111111110111111001111100001000000101 )
#1022002
b00101110101011001101010011010010 #
b0000000000000000000000000000000000101110101011001101010011010010 %
b00101110101011001101010011010010 '
b0000000000000000000000000000000000101110101011001101010011010010 )
#1023002
b10110111000011010000101110001101 #
b1111111111111111111111111111111110110111000011010000101110001101 %
b10110111000011010000101110001101 '
b1111111111111111111111111111111110110111000011010000101110001101 )
#1124002
b00101010111000001101011101111101 #
b0000000000000000000000000000000000101010111000001101011101111101 %
b00101010111000001101011101111101 '
b0000000000000000000000000000000000101010111000001101011101111101 )
#1125002
b11111011100000011111001100011011 #
b1111111111111111111111111111111111111011100000011111001100011011 %
b11111011100000011111001100011011 '
b1111111111111111111111111111111111111011100000011111001100011011 )
#1226002
b01000001101110000100011011100101 #
b0000000000000000000000000000000001000001101110000100011011100101 %
b01000001101110000100011011100101 '
b0000000000000000000000000000000001000001101110000100011011100101 )
#1227002
b11110100110110100100011000111100 #
b1111111111111111111111111111111111110100110110100100011000111100 %
b11110100110110100100011000111100 '
b1111111111111111111111111111111111110100110110100100011000111100 )
#1328002
b00110110000101111110100001101001 #
b0000000000000000000000000000000000110110000101111110100001101001 %
b00110110000101111110100001101001 '
b0000000000000000000000000000000000110110000101111110100001101001 )
#1329002
b10101110001010011111100111010000 #
b1111111111111111111111111111111110101110001010011111100111010000 %
b10101110001010011111100111010000 '
b1111111111111111111111111111111110101110001010011111100111010000 )
#1430002
b00000010001011000010010101101001 #
b0000000000000000000000000000000000000010001011000010010101101001 %
b00000010001011000010010101101001 '
b0000000000000000000000000000000000000010001011000010010101101001 )
#1431002
b11000111100000110101101100110011 #
b1111111111111111111111111111111111000111100000110101101100110011 %
b11000111100000110101101100110011 '
b1111111111111111111111111111111111000111100000110101101100110011 )
#1532002
b00000111011111110111100111000101 #
b0000000000000000000000000000000000000111011111110111100111000101 %
b00000111011111110111100111000101 '
b0000000000000000000000000000000000000111011111110111100111000101 )
#1533002
b11101001000100011000010000110011 #
b1111111111111111111111111111111111101001000100011000010000110011 %
b11101001000100011000010000110011 '
b1111111111111111111111111111111111101001000100011000010000110011 )
#1634002
b01101001101101000011001000101111 #
b0000000000000000000000000000000001101001101101000011001000101111 %
b01101001101101000011001000101111 '
b0000000000000000000000000000000001101001101101000011001000101111 )
#1635002
b11111110010000000100100010011111 #
b1111111111111111111111111111111111111110010000000100100010011111 %
b11111110010000000100100010011111 '
b1111111111111111111111111111111111111110010000000100100010011111 )
#1736002
b01101001100011010100001001100110 #
b0000000000000000000000000000000001101001100011010100001001100110 %
b01101001100011010100001001100110 '
b0000000000000000000000000000000001101001100011010100001001100110 )
#1737002
b10000110001100001000011100011101 #
b1111111111111111111111111111111110000110001100001000011100011101 %
b10000110001100001000011100011101 '
b1111111111111111111111111111111110000110001100001000011100011101 )
#1838002
b01010110111011100101001100110100 #
b0000000000000000000000000000000001010110111011100101001100110100 %
b01010110111011100101001100110100 '
b0000000000000000000000000000000001010110111011100101001100110100 )
#1839002
b10110001001100011011001000101011 #
b1111111111111111111111111111111110110001001100011011001000101011 %
b10110001001100011011001000101011 '
b1111111111111111111111111111111110110001001100011011001000101011 )
#1940002
b01000100110100011011000001010111 #
b0000000000000000000000000000000001000100110100011011000001010111 %
b01000100110100011011000001010111 '
b0000000000000000000000000000000001000100110100011011000001010111 )
#1941002
b10011000111010110101010001000110 #
b1111111111111111111111111111111110011000111010110101010001000110 %
b10011000111010110101010001000110 '
b1111111111111111111111111111111110011000111010110101010001000110 )
#2042002
b00001101011001101101001100001001 #
b0000000000000000000000000000000000001101011001101101001100001001 %
b00001101011001101101001100001001 '
b0000000000000000000000000000000000001101011001101101001100001001 )
#2043002
b11101110110101010010111100111100 #
b1111111111111111111111111111111111101110110101010010111100111100 %
b11101110110101010010111100111100 '
b1111111111111111111111111111111111101110110101010010111100111100 )
#2144002
b00111001001011011101000010010011 #
b0000000000000000000000000000000000111001001011011101000010010011 %
b00111001001011011101000010010011 '
b0000000000000000000000000000000000111001001011011101000010010011 )
#2145002
b10011100111001111101100110110010 #
b1111111111111111111111111111111110011100111001111101100110110010 %
b10011100111001111101100110110010 '
b1111111111111111111111111111111110011100111001111101100110110010 )
#2246002
b01111110110000010111000010100110 #
b0000000000000000000000000000000001111110110000010111000010100110 %
b01111110110000010111000010100110 '
b0000000000000000000000000000000001111110110000010111000010100110 )
#2247002
b10011010000110011101000011100000 #
b1111111111111111111111111111111110011010000110011101000011100000 %
b10011010000110011101000011100000 '
b1111111111111111111111111111111110011010000110011101000011100000 )
#2348002
b00000110011001101000111101000100 #
b0000000000000000000000000000000000000110011001101000111101000100 %
b00000110011001101000111101000100 '
b0000000000000000000000000000000000000110011001101000111101000100 )
#2349002
b11011100011101000111101011101110 #
b1111111111111111111111111111111111011100011101000111101011101110 %
b11011100011101000111101011101110 '
b1111111111111111111111111111111111011100011101000111101011101110 )
#2450002
b01110001111001001100010001101110 #
b0000000000000000000000000000000001110001111001001100010001101110 %
b01110001111001001100010001101110 '
b0000000000000000000000000000000001110001111001001100010001101110 )
#2451002
b10011111110111001100110110101101 #
b1111111111111111111111111111111110011111110111001100110110101101 %
b10011111110111001100110110101101 '
b1111111111111111111111111111111110011111110111001100110110101101 )
#2552002
b00110001010100110010011101010100 #
b0000000000000000000000000000000000110001010100110010011101010100 %
b00110001010100110010011101010100 '
b0000000000000000000000000000000000110001010100110010011101010100 )
#2553002
b10001100000100111111100101011100 #
b1111111111111111111111111111111110001100000100111111100101011100 %
b10001100000100111111100101011100 '
b1111111111111111111111111111111110001100000100111111100101011100 )
#2654002
b01101000011000110011111000101110 #
b0000000000000000000000000000000001101000011000110011111000101110 %
b01101000011000110011111000101110 '
b0000000000000000000000000000000001101000011000110011111000101110 )
#2655002
b11000000011101110000001100011111 #
b1111111111111111111111111111111111000000011101110000001100011111 %
b11000000011101110000001100011111 '
b1111111111111111111111111111111111000000011101110000001100011111 )
#2756002
b00100011011111111010001110011011 #
b0000000000000000000000000000000000100011011111111010001110011011 %
b00100011011111111010001110011011 '
b0000000000000000000000000000000000100011011111111010001110011011 )
#2757002
b10111000101010110001111110001010 #
b1111111111111111111111111111111110111000101010110001111110001010 %
b10111000101010110001111110001010 '
b1111111111111111111111111111111110111000101010110001111110001010 )
#2858002
b01000101111111111100001110110100 #
b0000000000000000000000000000000001000101111111111100001110110100 %
b01000101111111111100001110110100 '
b0000000000000000000000000000000001000101111111111100001110110100 )
#2859002
b11100110100111010111110010001011 #
b1111111111111111111111111111111111100110100111010111110010001011 %
b11100110100111010111110010001011 '
b1111111111111111111111111111111111100110100111010111110010001011 )
#2960002
b00100011000100010110011100100100 #
b0000000000000000000000000000000000100011000100010110011100100100 %
b00100011000100010110011100100100 '
b0000000000000000000000000000000000100011000100010110011100100100 )
#2961002
b10010111011101101110000101101111 #
b1111111111111111111111111111111110010111011101101110000101101111 %
b10010111011101101110000101101111 '
b1111111111111111111111111111111110010111011101101110000101101111 )
#3062002
b01100111111000111001110100101000 #
b0000000000000000000000000000000001100111111000111001110100101000 %
b01100111111000111001110100101000 '
b0000000000000000000000000000000001100111111000111001110100101000 )
#3063002
b11000001011011111001100001101111 #
b1111111111111111111111111111111111000001011011111001100001101111 %
b11000001011011111001100001101111 '
b1111111111111111111111111111111111000001011011111001100001101111 )
#3164002
b01111010011111100101001001100000 #
b0000000000000000000000000000000001111010011111100101001001100000 %
b01111010011111100101001001100000 '
b0000000000000000000000000000000001111010011111100101001001100000 )
#3165002
b11010100001100110010110000100011 #
b1111111111111111111111111111111111010100001100110010110000100011 %
b11010100001100110010110000100011 '
b1111111111111111111111111111111111010100001100110010110000100011 )
#3266002
b01110110100110101011110100000000 #
b0000000000000000000000000000000001110110100110101011110100000000 %
b01110110100110101011110100000000 '
b0000000000000000000000000000000001110110100110101011110100000000 )
#3267002
b10011001100100010100110000110110 #
b1111111111111111111111111111111110011001100100010100110000110110 %
b10011001100100010100110000110110 '
b1111111111111111111111111111111110011001100100010100110000110110 )
#3368002
b01000101000111111001000100001111 #
b0000000000000000000000000000000001000101000111111001000100001111 %
b01000101000111111001000100001111 '
b0000000000000000000000000000000001000101000111111001000100001111 )
#3369002
b10001111111110101111010110001010 #
b1111111111111111111111111111111110001111111110101111010110001010 %
b10001111111110101111010110001010 '
b1111111111111111111111111111111110001111111110101111010110001010 )
#3470002
b00001110000110110011000010100000 #
b0000000000000000000000000000000000001110000110110011000010100000 %
b00001110000110110011000010100000 '
b0000000000000000000000000000000000001110000110110011000010100000 )
#3471002
b10110000111001000101001100110101 #
b1111111111111111111111111111111110110000111001000101001100110101 %
b10110000111001000101001100110101 '
b1111111111111111111111111111111110110000111001000101001100110101 )
#3572002
b00110110100011111001000010001111 #
b0000000000000000000000000000000000110110100011111001000010001111 %
b00110110100011111001000010001111 '
b0000000000000000000000000000000000110110100011111001000010001111 )
#3573002
b11100010011001001100010111111111 #
b1111111111111111111111111111111111100010011001001100010111111111 %
b11100010011001001100010111111111 '
b1111111111111111111111111111111111100010011001001100010111111111 )
#3674002
b00101011101101011110101000000100 #
b0000000000000000000000000000000000101011101101011110101000000100 %
b00101011101101011110101000000100 '
b0000000000000000000000000000000000101011101101011110101000000100 )
#3675002
b11100111100000011110100110011111 #
b1111111111111111111111111111111111100111100000011110100110011111 %
b11100111100000011110100110011111 '
b1111111111111111111111111111111111100111100000011110100110011111 )
#3776002
b01001011010011001110110011001011 #
b0000000000000000000000000000000001001011010011001110110011001011 %
b01001011010011001110110011001011 '
b0000000000000000000000000000000001001011010011001110110011001011 )
#3777002
b10000101110101110101111001111100 #
b1111111111111111111111111111111110000101110101110101111001111100 %
b10000101110101110101111001111100 '
b1111111111111111111111111111111110000101110101110101111001111100 )
#3878002
b01101100110000110111110111111111 #
b0000000000000000000000000000000001101100110000110111110111111111 %
b01101100110000110111110111111111 '
b0000000000000000000000000000000001101100110000110111110111111111 )
#3879002
b10001011001011010101101100110111 #
b1111111111111111111111111111111110001011001011010101101100110111 %
b10001011001011010101101100110111 '
b1111111111111111111111111111111110001011001011010101101100110111 )
#3980002
b01111100100101000001100010110010 #
b0000000000000000000000000000000001111100100101000001100010110010 %
b01111100100101000001100010110010 '
b0000000000000000000000000000000001111100100101000001100010110010 )
#3981002
b11000001100100110111011100100110 #
b1111111111111111111111111111111111000001100100110111011100100110 %
b11000001100100110111011100100110 '
b1111111111111111111111111111111111000001100100110111011100100110 )
#4082002
b01011001000100010010000110000010 #
b0000000000000000000000000000000001011001000100010010000110000010 %
b01011001000100010010000110000010 '
b0000000000000000000000000000000001011001000100010010000110000010 )
#4083002
b11110100001101010100100111111101 #
b1111111111111111111111111111111111110100001101010100100111111101 %
b11110100001101010100100111111101 '
b1111111111111111111111111111111111110100001101010100100111111101 )
#4184002
b00011010000011001001100110111111 #
b0000000000000000000000000000000000011010000011001001100110111111 %
b00011010000011001001100110111111 '
b0000000000000000000000000000000000011010000011001001100110111111 )
#4185002
b11010101111111111011010000111001 #
b1111111111111111111111111111111111010101111111111011010000111001 %
b11010101111111111011010000111001 '
b1111111111111111111111111111111111010101111111111011010000111001 )
#4286002
b00000111010000000011011001011001 #
b0000000000000000000000000000000000000111010000000011011001011001 %
b00000111010000000011011001011001 '
b0000000000000000000000000000000000000111010000000011011001011001 )
#4287002
b11110100010001011000101110101100 #
b1111111111111111111111111111111111110100010001011000101110101100 %
b11110100010001011000101110101100 '
b1111111111111111111111111111111111110100010001011000101110101100 )
#4388002
b00010100110011100011100011011101 #
b0000000000000000000000000000000000010100110011100011100011011101 %
b00010100110011100011100011011101 '
b0000000000000000000000000000000000010100110011100011100011011101 )
#4389002
b11100100101100010000110010011111 #
b1111111111111111111111111111111111100100101100010000110010011111 %
b11100100101100010000110010011111 '
b1111111111111111111111111111111111100100101100010000110010011111 )
#4490002
b00111110101110110100110011000010 #
b0000000000000000000000000000000000111110101110110100110011000010 %
b00111110101110110100110011000010 '
b0000000000000000000000000000000000111110101110110100110011000010 )
#4491002
b10100100110100111100101110000101 #
b1111111111111111111111111111111110100100110100111100101110000101 %
b10100100110100111100101110000101 '
b1111111111111111111111111111111110100100110100111100101110000101 )
#4592002
b01011010011010011011111110001001 #
b0000000000000000000000000000000001011010011010011011111110001001 %
b01011010011010011011111110001001 '
b0000000000000000000000000000000001011010011010011011111110001001 )
#4593002
b10011000000100010011000110101110 #
b1111111111111111111111111111111110011000000100010011000110101110 %
b10011000000100010011000110101110 '
b1111111111111111111111111111111110011000000100010011000110101110 )
#4694002
b01001011011111100101011001000011 #
b0000000000000000000000000000000001001011011111100101011001000011 %
b01001011011111100101011001000011 '
b0000000000000000000000000000000001001011011111100101011001000011 )
#4695002
b10100111010111111011110000001010 #
b1111111111111111111111111111111110100111010111111011110000001010 %
b10100111010111111011110000001010 '
b1111111111111111111111111111111110100111010111111011110000001010 )
#4796002
b01111010010111110111110000110001 #
b0000000000000000000000000000000001111010010111110111110000110001 %
b01111010010111110111110000110001 '
b0000000000000000000000000000000001111010010111110111110000110001 )
#4797002
b10110100110000010100010101000101 #
b1111111111111111111111111111111110110100110000010100010101000101 %
b10110100110000010100010101000101 '
b1111111111111111111111111111111110110100110000010100010101000101 )
#4898002
b00010001111111011110101101100010 #
b0000000000000000000000000000000000010001111111011110101101100010 %
b00010001111111011110101101100010 '
b0000000000000000000000000000000000010001111111011110101101100010 )
#4899002
b11100111111011011001101100001010 #
b1111111111111111111111111111111111100111111011011001101100001010 %
b11100111111011011001101100001010 '
b1111111111111111111111111111111111100111111011011001101100001010 )
#5000002
b00110110010001000101101111001100 #
b0000000000000000000000000000000000110110010001000101101111001100 %
b00110110010001000101101111001100 '
b0000000000000000000000000000000000110110010001000101101111001100 )
#5001002
b10101110100101010001010100101001 #
b1111111111111111111111111111111110101110100101010001010100101001 %
b10101110100101010001010100101001 '
b1111111111111111111111111111111110101110100101010001010100101001 )
#5102002
b01011011000101011100001101110101 #
b0000000000000000000000000000000001011011000101011100001101110101 %
b01011011000101011100001101110101 '
b0000000000000000000000000000000001011011000101011100001101110101 )
#5103002
b11110001001010001011000110001011 #
b1111111111111111111111111111111111110001001010001011000110001011 %
b11110001001010001011000110001011 '
b1111111111111111111111111111111111110001001010001011000110001011 )
#5204002
b00101100000100110100110010111111 #
b0000000000000000000000000000000000101100000100110100110010111111 %
b00101100000100110100110010111111 '
b0000000000000000000000000000000000101100000100110100110010111111 )
#5205002
b11001110001100001111100010001110 #
b1111111111111111111111111111111111001110001100001111100010001110 %
b11001110001100001111100010001110 '
b1111111111111111111111111111111111001110001100001111100010001110 )
#5306002
b01010001001100000000111010100001 #
b0000000000000000000000000000000001010001001100000000111010100001 %
b01010001001100000000111010100001 '
b0000000000000000000000000000000001010001001100000000111010100001 )
#5307002
b10011101101010000010011110001111 #
b1111111111111111111111111111111110011101101010000010011110001111 %
b10011101101010000010011110001111 '
b1111111111111111111111111111111110011101101010000010011110001111 )
#5408002
b01110111110001111010000011110010 #
b0000000000000000000000000000000001110111110001111010000011110010 %
b01110111110001111010000011110010 '
b0000000000000000000000000000000001110111110001111010000011110010 )
#5409002
b11001010000010101110011110101110 #
b1111111111111111111111111111111111001010000010101110011110101110 %
b11001010000010101110011110101110 '
b1111111111111111111111111111111111001010000010101110011110101110 )
#5510002
b01111110000010011110001100010101 #
b0000000000000000000000000000000001111110000010011110001100010101 %
b01111110000010011110001100010101 '
b0000000000000000000000000000000001111110000010011110001100010101 )
#5511002
b11000000111110110010000111101110 #
b1111111111111111111111111111111111000000111110110010000111101110 %
b11000000111110110010000111101110 '
b1111111111111111111111111111111111000000111110110010000111101110 )
#5612002
b00101011101001111010010111101111 #
b0000000000000000000000000000000000101011101001111010010111101111 %
b00101011101001111010010111101111 '
b0000000000000000000000000000000000101011101001111010010111101111 )
#5613002
b10111001100100001111001100110010 #
b1111111111111111111111111111111110111001100100001111001100110010 %
b10111001100100001111001100110010 '
b1111111111111111111111111111111110111001100100001111001100110010 )
#5714002
b00111100111101000100001010101110 #
b0000000000000000000000000000000000111100111101000100001010101110 %
b00111100111101000100001010101110 '
b0000000000000000000000000000000000111100111101000100001010101110 )
#5715002
b11011011101011010110010010111010 #
b1111111111111111111111111111111111011011101011010110010010111010 %
b11011011101011010110010010111010 '
b1111111111111111111111111111111111011011101011010110010010111010 )
#5816002
b00110110111001000001001011010101 #
b0000000000000000000000000000000000110110111001000001001011010101 %
b00110110111001000001001011010101 '
b0000000000000000000000000000000000110110111001000001001011010101 )
#5817002
b10010010110100111011011100101001 #
b1111111111111111111111111111111110010010110100111011011100101001 %
b10010010110100111011011100101001 '
b1111111111111111111111111111111110010010110100111011011100101001 )
#5918002
b01101011111001010011011010001110 #
b0000000000000000000000000000000001101011111001010011011010001110 %
b01101011111001010011011010001110 '
b0000000000000000000000000000000001101011111001010011011010001110 )
#5919002
b11011011011111110000110011111001 #
b1111111111111111111111111111111111011011011111110000110011111001 %
b11011011011111110000110011111001 '
b1111111111111111111111111111111111011011011111110000110011111001 )
#6020002
b01110011010100000000110101110000 #
b0000000000000000000000000000000001110011010100000000110101110000 %
b01110011010100000000110101110000 '
b0000000000000000000000000000000001110011010100000000110101110000 )
#6021002
b10011100111100010111110101100111 #
b1111111111111111111111111111111110011100111100010111110101100111 %
b10011100111100010111110101100111 '
b1111111111111111111111111111111110011100111100010111110101100111 )
#6122002
b00000010111011000100101000001101 #
b0000000000000000000000000000000000000010111011000100101000001101 %
b00000010111011000100101000001101 '
b0000000000000000000000000000000000000010111011000100101000001101 )
#6123002
b10111000111111100111101101111100 #
b1111111111111111111111111111111110111000111111100111101101111100 %
b10111000111111100111101101111100 '
b1111111111111111111111111111111110111000111111100111101101111100 )
#6224002
b00101100100111010100101010100100 #
b0000000000000000000000000000000000101100100111010100101010100100 %
b00101100100111010100101010100100 '
b0000000000000000000000000000000000101100100111010100101010100100 )
#6225002
b11111001101110010111010001010000 #
b1111111111111111111111111111111111111001101110010111010001010000 %
b11111001101110010111010001010000 '
b1111111111111111111111111111111111111001101110010111010001010000 )
#6326002
b00111110000101101100000000001110 #
b0000000000000000000000000000000000111110000101101100000000001110 %
b00111110000101101100000000001110 '
b0000000000000000000000000000000000111110000101101100000000001110 )
#6327002
b11100010101101111100000111001101 #
b1111111111111111111111111111111111100010101101111100000111001101 %
b11100010101101111100000111001101 '
b1111111111111111111111111111111111100010101101111100000111001101 )
#6428002
b00001000001001111100000110110000 #
b0000000000000000000000000000000000001000001001111100000110110000 %
b00001000001001111100000110110000 '
b0000000000000000000000000000000000001000001001111100000110110000 )
#6429002
b10111110101010001011001110001111 #
b1111111111111111111111111111111110111110101010001011001110001111 %
b10111110101010001011001110001111 '
b1111111111111111111111111111111110111110101010001011001110001111 )
#6530002
b00111001111000001100010101011101 #
b0000000000000000000000000000000000111001111000001100010101011101 %
b00111001111000001100010101011101 '
b0000000000000000000000000000000000111001111000001100010101011101 )
#6531002
b11110001010010101100010111111100 #
b1111111111111111111111111111111111110001010010101100010111111100 %
b11110001010010101100010111111100 '
b1111111111111111111111111111111111110001010010101100010111111100 )
#6632002
b00110111001101111011100000111010 #
b0000000000000000000000000000000000110111001101111011100000111010 %
b00110111001101111011100000111010 '
b0000000000000000000000000000000000110111001101111011100000111010 )
#6633002
b10011000010011111100011001000110 #
b1111111111111111111111111111111110011000010011111100011001000110 %
b10011000010011111100011001000110 '
b1111111111111111111111111111111110011000010011111100011001000110 )
#6734002
b01010100000011110100110001000010 #
b0000000000000000000000000000000001010100000011110100110001000010 %
b01010100000011110100110001000010 '
b0000000000000000000000000000000001010100000011110100110001000010 )
#6735002
b10001111111001011001101001011101 #
b1111111111111111111111111111111110001111111001011001101001011101 %
b10001111111001011001101001011101 '
b1111111111111111111111111111111110001111111001011001101001011101 )
#6836002
b00110010100110100010000001000100 #
b0000000000000000000000000000000000110010100110100010000001000100 %
b00110010100110100010000001000100 '
b0000000000000000000000000000000000110010100110100010000001000100 )
#6837002
b11001011010001000011111000110111 #
b1111111111111111111111111111111111001011010001000011111000110111 %
b11001011010001000011111000110111 '
b1111111111111111111111111111111111001011010001000011111000110111 )
#6938002
b01010110110001101001000111001111 #
b0000000000000000000000000000000001010110110001101001000111001111 %
b01010110110001101001000111001111 '
b0000000000000000000000000000000001010110110001101001000111001111 )
#6939002
b11101100001111111100010100110111 #
b1111111111111111111111111111111111101100001111111100010100110111 %
b11101100001111111100010100110111 '
b1111111111111111111111111111111111101100001111111100010100110111 )
#7040002
b00000010100011100000100010011000 #
b0000000000000000000000000000000000000010100011100000100010011000 %
b00000010100011100000100010011000 '
b0000000000000000000000000000000000000010100011100000100010011000 )
#7041002
b11100000011111101010011101001011 #
b1111111111111111111111111111111111100000011111101010011101001011 %
b11100000011111101010011101001011 '
b1111111111111111111111111111111111100000011111101010011101001011 )
#7142002
b01100011001010100100001100010110 #
b0000000000000000000000000000000001100011001010100100001100010110 %
b01100011001010100100001100010110 '
b0000000000000000000000000000000001100011001010100100001100010110 )
#7143002
b11101110100001101110100111001111 #
b1111111111111111111111111111111111101110100001101110100111001111 %
b11101110100001101110100111001111 '
b1111111111111111111111111111111111101110100001101110100111001111 )
#7244002
b00100001000100010110110101010010 #
b0000000000000000000000000000000000100001000100010110110101010010 %
b00100001000100010110110101010010 '
b0000000000000000000000000000000000100001000100010110110101010010 )
#7245002
b11000000000100101001100001000111 #
b1111111111111111111111111111111111000000000100101001100001000111 %
b11000000000100101001100001000111 '
b1111111111111111111111111111111111000000000100101001100001000111 )
#7346002
b01000010110010111011101000001110 #
b0000000000000000000000000000000001000010110010111011101000001110 %
b01000010110010111011101000001110 '
b0000000000000000000000000000000001000010110010111011101000001110 )
#7347002
b11011101010100101011011111011010 #
b1111111111111111111111111111111111011101010100101011011111011010 %
b11011101010100101011011111011010 '
b1111111111111111111111111111111111011101010100101011011111011010 )
#7448002
b01111001110000101000010011000101 #
b0000000000000000000000000000000001111001110000101000010011000101 %
b01111001110000101000010011000101 '
b0000000000000000000000000000000001111001110000101000010011000101 )
#7449002
b10101110101001100110110010110011 #
b1111111111111111111111111111111110101110101001100110110010110011 %
b10101110101001100110110010110011 '
b1111111111111111111111111111111110101110101001100110110010110011 )
#7550002
b01000001110110110100001100010011 #
b0000000000000000000000000000000001000001110110110100001100010011 %
b01000001110110110100001100010011 '
b0000000000000000000000000000000001000001110110110100001100010011 )
#7551002
b11101100110001011010011100111111 #
b1111111111111111111111111111111111101100110001011010011100111111 %
b11101100110001011010011100111111 '
b1111111111111111111111111111111111101100110001011010011100111111 )
#7652002
b00100110100011010100011011100010 #
b0000000000000000000000000000000000100110100011010100011011100010 %
b00100110100011010100011011100010 '
b0000000000000000000000000000000000100110100011010100011011100010 )
#7653002
b11001100110001111001100011110000 #
b1111111111111111111111111111111111001100110001111001100011110000 %
b11001100110001111001100011110000 '
b1111111111111111111111111111111111001100110001111001100011110000 )
#7754002
b00111100100011101111100110101111 #
b0000000000000000000000000000000000111100100011101111100110101111 %
b00111100100011101111100110101111 '
b0000000000000000000000000000000000111100100011101111100110101111 )
#7755002
b10101011000110111111011000010010 #
b1111111111111111111111111111111110101011000110111111011000010010 %
b10101011000110111111011000010010 '
b1111111111111111111111111111111110101011000110111111011000010010 )
#7856002
b00100010100110100110101110001111 #
b0000000000000000000000000000000000100010100110100110101110001111 %
b00100010100110100110101110001111 '
b0000000000000000000000000000000000100010100110100110101110001111 )
#7857002
b11000111111010000110001111000000 #
b1111111111111111111111111111111111000111111010000110001111000000 %
b11000111111010000110001111000000 '
b1111111111111111111111111111111111000111111010000110001111000000 )
#7958002
b00010101111101100000101111110000 #
b0000000000000000000000000000000000010101111101100000101111110000 %
b00010101111101100000101111110000 '
b0000000000000000000000000000000000010101111101100000101111110000 )
#7959002
b10110010111110110010111101000011 #
b1111111111111111111111111111111110110010111110110010111101000011 %
b10110010111110110010111101000011 '
b1111111111111111111111111111111110110010111110110010111101000011 )
#8060002
b00010111101010111001000011111110 #
b0000000000000000000000000000000000010111101010111001000011111110 %
b00010111101010111001000011111110 '
b0000000000000000000000000000000000010111101010111001000011111110 )
#8061002
b10010010111110101110110111000001 #
b1111111111111111111111111111111110010010111110101110110111000001 %
b10010010111110101110110111000001 '
b1111111111111111111111111111111110010010111110101110110111000001 )
#8162002
b00011101001011011011001010010000 #
b0000000000000000000000000000000000011101001011011011001010010000 %
b00011101001011011011001010010000 '
b0000000000000000000000000000000000011101001011011011001010010000 )
