memory/memory.sv
// memory.sv for ZEAL

module memory #(
    parameter WORDS = 128,
    parameter mem_init = ""
) (
    input logic clk,
    input logic [63:0] address, //We are doing 64-bit memory addresses and data!
    input logic [63:0] write_data,
    input logic [7:0] byte_enable,
    input logic write_enable,
    input logic rst_n,

    output logic [63:0] read_data
);

/*
* This memory is byte addressed
* but we have currently no support for mis-aligned writes nor reads.
*/

reg [63:0] mem [0:WORDS-1]; // Memory array of words (64-bits)

initial begin
    if (mem_init != "") begin
        $readmemh(mem_init, mem);
    end
end

/* verilator lint_off WIDTHTRUNC */
always @(posedge clk) begin
    // reset logic
    if (rst_n == 1'b0) begin
        for (int i=0; i < WORDS; i++) begin
            mem[i] <= 64'b0;
        end
    end
    else if (write_enable) begin
        if (address[2:0] != 3'b000) begin
            $display("Misaligned write at address %h", address);
        end else begin
            // use byte-enable to selectively write bytes
            for (int i= 0; i< 8; i++) begin
                if (byte_enable[i]) begin
                    mem[address[63:3]][(i*8)+:8] <= write_data[(i*8)+:8];
                end
            end
        end
    end
end

// Read logic
always_comb begin
    //here, address [63:3] is the word index
    read_data = mem[address[63:3]];
end
/* verilator lint_on WIDTHTRUNC */
endmodule

memory/dump.vcd
$version Generated by VerilatedVcd $end
$timescale 1ps $end
 $scope module $rootio $end
  $var wire 1 # clk $end
  $var wire 64 $ address [63:0] $end
  $var wire 64 & write_data [63:0] $end
  $var wire 8 ( byte_enable [7:0] $end
  $var wire 1 ) write_enable $end
  $var wire 1 * rst_n $end
  $var wire 64 + read_data [63:0] $end
 $upscope $end
 $scope module memory $end
  $var wire 32 9 WORDS [31:0] $end
  $var wire 8 : mem_init [7:0] $end
  $var wire 1 - clk $end
  $var wire 64 . address [63:0] $end
  $var wire 64 0 write_data [63:0] $end
  $var wire 8 2 byte_enable [7:0] $end
  $var wire 1 3 write_enable $end
  $var wire 1 4 rst_n $end
  $var wire 64 5 read_data [63:0] $end
  $scope module unnamedblk1 $end
   $var wire 32 7 i [31:0] $end
  $upscope $end
  $scope module unnamedblk2 $end
   $var wire 32 8 i [31:0] $end
  $upscope $end
 $upscope $end
$enddefinitions $end


#0
1#
b0000000000000000000000000000000000000000000000000000000000000000 $
b0000000000000000000000000000000000000000000000000000000000000000 &
b00000000 (
0)
0*
b0000000000000000000000000000000000000000000000000000000000000000 +
1-
b0000000000000000000000000000000000000000000000000000000000000000 .
b0000000000000000000000000000000000000000000000000000000000000000 0
b00000000 2
03
04
b0000000000000000000000000000000000000000000000000000000000000000 5
b00000000000000000000000010000000 7
b00000000000000000000000000000000 8
b00000000000000000000000010000000 9
b00000000 :
#500
0#
0-
#1000
1#
1*
1-
14
#1500
0#
0-
#2000
1#
1-
#2500
0#
0-
#3000
1#
b0000000000000000000000000000000000000000000000000000000000000001 $
1-
b0000000000000000000000000000000000000000000000000000000000000001 .
#3500
0#
0-
#4000
1#
b0000000000000000000000000000000000000000000000000000000000000010 $
1-
b0000000000000000000000000000000000000000000000000000000000000010 .
#4500
0#
0-
#5000
1#
b0000000000000000000000000000000000000000000000000000000000000011 $
1-
b0000000000000000000000000000000000000000000000000000000000000011 .
#5500
0#
0-
#6000
1#
b0000000000000000000000000000000000000000000000000000000000000100 $
1-
b0000000000000000000000000000000000000000000000000000000000000100 .
#6500
0#
0-
#7000
1#
b0000000000000000000000000000000000000000000000000000000000000101 $
1-
b0000000000000000000000000000000000000000000000000000000000000101 .
#7500
0#
0-
#8000
1#
b0000000000000000000000000000000000000000000000000000000000000110 $
1-
b0000000000000000000000000000000000000000000000000000000000000110 .
#8500
0#
0-
#9000
1#
b0000000000000000000000000000000000000000000000000000000000000111 $
1-
b0000000000000000000000000000000000000000000000000000000000000111 .
#9500
0#
0-
#10000
1#
b0000000000000000000000000000000000000000000000000000000000001000 $
1-
b0000000000000000000000000000000000000000000000000000000000001000 .
#10500
0#
0-
#11000
1#
b0000000000000000000000000000000000000000000000000000000000001001 $
1-
b0000000000000000000000000000000000000000000000000000000000001001 .
#11500
0#
0-
#12000
1#
b0000000000000000000000000000000000000000000000000000000000001010 $
1-
b0000000000000000000000000000000000000000000000000000000000001010 .
#12500
0#
0-
#13000
1#
b0000000000000000000000000000000000000000000000000000000000001011 $
1-
b0000000000000000000000000000000000000000000000000000000000001011 .
#13500
0#
0-
#14000
1#
b0000000000000000000000000000000000000000000000000000000000001100 $
1-
b0000000000000000000000000000000000000000000000000000000000001100 .
#14500
0#
0-
#15000
1#
b0000000000000000000000000000000000000000000000000000000000001101 $
1-
b0000000000000000000000000000000000000000000000000000000000001101 .
#15500
0#
0-
#16000
1#
b0000000000000000000000000000000000000000000000000000000000001110 $
1-
b0000000000000000000000000000000000000000000000000000000000001110 .
#16500
0#
0-
#17000
1#
b0000000000000000000000000000000000000000000000000000000000001111 $
1-
b0000000000000000000000000000000000000000000000000000000000001111 .
#17500
0#
0-
#18000
1#
b0000000000000000000000000000000000000000000000000000000000010000 $
1-
b0000000000000000000000000000000000000000000000000000000000010000 .
#18500
0#
0-
#19000
1#
b0000000000000000000000000000000000000000000000000000000000010001 $
1-
b0000000000000000000000000000000000000000000000000000000000010001 .
#19500
0#
0-
#20000
1#
b0000000000000000000000000000000000000000000000000000000000010010 $
1-
b0000000000000000000000000000000000000000000000000000000000010010 .
#20500
0#
0-
#21000
1#
b0000000000000000000000000000000000000000000000000000000000010011 $
1-
b0000000000000000000000000000000000000000000000000000000000010011 .
#21500
0#
0-
#22000
1#
b0000000000000000000000000000000000000000000000000000000000010100 $
1-
b0000000000000000000000000000000000000000000000000000000000010100 .
#22500
0#
0-
#23000
1#
b0000000000000000000000000000000000000000000000000000000000010101 $
1-
b0000000000000000000000000000000000000000000000000000000000010101 .
#23500
0#
0-
#24000
1#
b0000000000000000000000000000000000000000000000000000000000010110 $
1-
b0000000000000000000000000000000000000000000000000000000000010110 .
#24500
0#
0-
#25000
1#
b0000000000000000000000000000000000000000000000000000000000010111 $
1-
b0000000000000000000000000000000000000000000000000000000000010111 .
#25500
0#
0-
#26000
1#
b0000000000000000000000000000000000000000000000000000000000011000 $
1-
b0000000000000000000000000000000000000000000000000000000000011000 .
#26500
0#
0-
#27000
1#
b0000000000000000000000000000000000000000000000000000000000011001 $
1-
b0000000000000000000000000000000000000000000000000000000000011001 .
#27500
0#
0-
#28000
1#
b0000000000000000000000000000000000000000000000000000000000011010 $
1-
b0000000000000000000000000000000000000000000000000000000000011010 .
#28500
0#
0-
#29000
1#
b0000000000000000000000000000000000000000000000000000000000011011 $
1-
b0000000000000000000000000000000000000000000000000000000000011011 .
#29500
0#
0-
#30000
1#
b0000000000000000000000000000000000000000000000000000000000011100 $
1-
b0000000000000000000000000000000000000000000000000000000000011100 .
#30500
0#
0-
#31000
1#
b0000000000000000000000000000000000000000000000000000000000011101 $
1-
b0000000000000000000000000000000000000000000000000000000000011101 .
#31500
0#
0-
#32000
1#
b0000000000000000000000000000000000000000000000000000000000011110 $
1-
b0000000000000000000000000000000000000000000000000000000000011110 .
#32500
0#
0-
#33000
1#
b0000000000000000000000000000000000000000000000000000000000011111 $
1-
b0000000000000000000000000000000000000000000000000000000000011111 .
#33500
0#
0-
#34000
1#
b0000000000000000000000000000000000000000000000000000000000100000 $
1-
b0000000000000000000000000000000000000000000000000000000000100000 .
#34500
0#
0-
#35000
1#
b0000000000000000000000000000000000000000000000000000000000100001 $
1-
b0000000000000000000000000000000000000000000000000000000000100001 .
#35500
0#
0-
#36000
1#
b0000000000000000000000000000000000000000000000000000000000100010 $
1-
b0000000000000000000000000000000000000000000000000000000000100010 .
#36500
0#
0-
#37000
1#
b0000000000000000000000000000000000000000000000000000000000100011 $
1-
b0000000000000000000000000000000000000000000000000000000000100011 .
#37500
0#
0-
#38000
1#
b0000000000000000000000000000000000000000000000000000000000100100 $
1-
b0000000000000000000000000000000000000000000000000000000000100100 .
#38500
0#
0-
#39000
1#
b0000000000000000000000000000000000000000000000000000000000100101 $
1-
b0000000000000000000000000000000000000000000000000000000000100101 .
#39500
0#
0-
#40000
1#
b0000000000000000000000000000000000000000000000000000000000100110 $
1-
b0000000000000000000000000000000000000000000000000000000000100110 .
#40500
0#
0-
#41000
1#
b0000000000000000000000000000000000000000000000000000000000100111 $
1-
b0000000000000000000000000000000000000000000000000000000000100111 .
#41500
0#
0-
#42000
1#
b0000000000000000000000000000000000000000000000000000000000101000 $
1-
b0000000000000000000000000000000000000000000000000000000000101000 .
#42500
0#
0-
#43000
1#
b0000000000000000000000000000000000000000000000000000000000101001 $
1-
b0000000000000000000000000000000000000000000000000000000000101001 .
#43500
0#
0-
#44000
1#
b0000000000000000000000000000000000000000000000000000000000101010 $
1-
b0000000000000000000000000000000000000000000000000000000000101010 .
#44500
0#
0-
#45000
1#
b0000000000000000000000000000000000000000000000000000000000101011 $
1-
b0000000000000000000000000000000000000000000000000000000000101011 .
#45500
0#
0-
#46000
1#
b0000000000000000000000000000000000000000000000000000000000101100 $
1-
b0000000000000000000000000000000000000000000000000000000000101100 .
#46500
0#
0-
#47000
1#
b0000000000000000000000000000000000000000000000000000000000101101 $
1-
b0000000000000000000000000000000000000000000000000000000000101101 .
#47500
0#
0-
#48000
1#
b0000000000000000000000000000000000000000000000000000000000101110 $
1-
b0000000000000000000000000000000000000000000000000000000000101110 .
#48500
0#
0-
#49000
1#
b0000000000000000000000000000000000000000000000000000000000101111 $
1-
b0000000000000000000000000000000000000000000000000000000000101111 .
#49500
0#
0-
#50000
1#
b0000000000000000000000000000000000000000000000000000000000110000 $
1-
b0000000000000000000000000000000000000000000000000000000000110000 .
#50500
0#
0-
#51000
1#
b0000000000000000000000000000000000000000000000000000000000110001 $
1-
b0000000000000000000000000000000000000000000000000000000000110001 .
#51500
0#
0-
#52000
1#
b0000000000000000000000000000000000000000000000000000000000110010 $
1-
b0000000000000000000000000000000000000000000000000000000000110010 .
#52500
0#
0-
#53000
1#
b0000000000000000000000000000000000000000000000000000000000110011 $
1-
b0000000000000000000000000000000000000000000000000000000000110011 .
#53500
0#
0-
#54000
1#
b0000000000000000000000000000000000000000000000000000000000110100 $
1-
b0000000000000000000000000000000000000000000000000000000000110100 .
#54500
0#
0-
#55000
1#
b0000000000000000000000000000000000000000000000000000000000110101 $
1-
b0000000000000000000000000000000000000000000000000000000000110101 .
#55500
0#
0-
#56000
1#
b0000000000000000000000000000000000000000000000000000000000110110 $
1-
b0000000000000000000000000000000000000000000000000000000000110110 .
#56500
0#
0-
#57000
1#
b0000000000000000000000000000000000000000000000000000000000110111 $
1-
b0000000000000000000000000000000000000000000000000000000000110111 .
#57500
0#
0-
#58000
1#
b0000000000000000000000000000000000000000000000000000000000111000 $
1-
b0000000000000000000000000000000000000000000000000000000000111000 .
#58500
0#
0-
#59000
1#
b0000000000000000000000000000000000000000000000000000000000111001 $
1-
b0000000000000000000000000000000000000000000000000000000000111001 .
#59500
0#
0-
#60000
1#
b0000000000000000000000000000000000000000000000000000000000111010 $
1-
b0000000000000000000000000000000000000000000000000000000000111010 .
#60500
0#
0-
#61000
1#
b0000000000000000000000000000000000000000000000000000000000111011 $
1-
b0000000000000000000000000000000000000000000000000000000000111011 .
#61500
0#
0-
#62000
1#
b0000000000000000000000000000000000000000000000000000000000111100 $
1-
b0000000000000000000000000000000000000000000000000000000000111100 .
#62500
0#
0-
#63000
1#
b0000000000000000000000000000000000000000000000000000000000111101 $
1-
b0000000000000000000000000000000000000000000000000000000000111101 .
#63500
0#
0-
#64000
1#
b0000000000000000000000000000000000000000000000000000000000111110 $
1-
b0000000000000000000000000000000000000000000000000000000000111110 .
#64500
0#
0-
#65000
1#
b0000000000000000000000000000000000000000000000000000000000111111 $
1-
b0000000000000000000000000000000000000000000000000000000000111111 .
#65500
0#
0-
#66000
1#
b0000000000000000000000000000000000000000000000000000000001000000 $
1-
b0000000000000000000000000000000000000000000000000000000001000000 .
#66500
0#
0-
#67000
1#
b0000000000000000000000000000000000000000000000000000000001000001 $
1-
b0000000000000000000000000000000000000000000000000000000001000001 .
#67500
0#
0-
#68000
1#
b0000000000000000000000000000000000000000000000000000000001000010 $
1-
b0000000000000000000000000000000000000000000000000000000001000010 .
#68500
0#
0-
#69000
1#
b0000000000000000000000000000000000000000000000000000000001000011 $
1-
b0000000000000000000000000000000000000000000000000000000001000011 .
#69500
0#
0-
#70000
1#
b0000000000000000000000000000000000000000000000000000000001000100 $
1-
b0000000000000000000000000000000000000000000000000000000001000100 .
#70500
0#
0-
#71000
1#
b0000000000000000000000000000000000000000000000000000000001000101 $
1-
b0000000000000000000000000000000000000000000000000000000001000101 .
#71500
0#
0-
#72000
1#
b0000000000000000000000000000000000000000000000000000000001000110 $
1-
b0000000000000000000000000000000000000000000000000000000001000110 .
#72500
0#
0-
#73000
1#
b0000000000000000000000000000000000000000000000000000000001000111 $
1-
b0000000000000000000000000000000000000000000000000000000001000111 .
#73500
0#
0-
#74000
1#
b0000000000000000000000000000000000000000000000000000000001001000 $
1-
b0000000000000000000000000000000000000000000000000000000001001000 .
#74500
0#
0-
#75000
1#
b0000000000000000000000000000000000000000000000000000000001001001 $
1-
b0000000000000000000000000000000000000000000000000000000001001001 .
#75500
0#
0-
#76000
1#
b0000000000000000000000000000000000000000000000000000000001001010 $
1-
b0000000000000000000000000000000000000000000000000000000001001010 .
#76500
0#
0-
#77000
1#
b0000000000000000000000000000000000000000000000000000000001001011 $
1-
b0000000000000000000000000000000000000000000000000000000001001011 .
#77500
0#
0-
#78000
1#
b0000000000000000000000000000000000000000000000000000000001001100 $
1-
b0000000000000000000000000000000000000000000000000000000001001100 .
#78500
0#
0-
#79000
1#
b0000000000000000000000000000000000000000000000000000000001001101 $
1-
b0000000000000000000000000000000000000000000000000000000001001101 .
#79500
0#
0-
#80000
1#
b0000000000000000000000000000000000000000000000000000000001001110 $
1-
b0000000000000000000000000000000000000000000000000000000001001110 .
#80500
0#
0-
#81000
1#
b0000000000000000000000000000000000000000000000000000000001001111 $
1-
b0000000000000000000000000000000000000000000000000000000001001111 .
#81500
0#
0-
#82000
1#
b0000000000000000000000000000000000000000000000000000000001010000 $
1-
b0000000000000000000000000000000000000000000000000000000001010000 .
#82500
0#
0-
#83000
1#
b0000000000000000000000000000000000000000000000000000000001010001 $
1-
b0000000000000000000000000000000000000000000000000000000001010001 .
#83500
0#
0-
#84000
1#
b0000000000000000000000000000000000000000000000000000000001010010 $
1-
b0000000000000000000000000000000000000000000000000000000001010010 .
#84500
0#
0-
#85000
1#
b0000000000000000000000000000000000000000000000000000000001010011 $
1-
b0000000000000000000000000000000000000000000000000000000001010011 .
#85500
0#
0-
#86000
1#
b0000000000000000000000000000000000000000000000000000000001010100 $
1-
b0000000000000000000000000000000000000000000000000000000001010100 .
#86500
0#
0-
#87000
1#
b0000000000000000000000000000000000000000000000000000000001010101 $
1-
b0000000000000000000000000000000000000000000000000000000001010101 .
#87500
0#
0-
#88000
1#
b0000000000000000000000000000000000000000000000000000000001010110 $
1-
b0000000000000000000000000000000000000000000000000000000001010110 .
#88500
0#
0-
#89000
1#
b0000000000000000000000000000000000000000000000000000000001010111 $
1-
b0000000000000000000000000000000000000000000000000000000001010111 .
#89500
0#
0-
#90000
1#
b0000000000000000000000000000000000000000000000000000000001011000 $
1-
b0000000000000000000000000000000000000000000000000000000001011000 .
#90500
0#
0-
#91000
1#
b0000000000000000000000000000000000000000000000000000000001011001 $
1-
b0000000000000000000000000000000000000000000000000000000001011001 .
#91500
0#
0-
#92000
1#
b0000000000000000000000000000000000000000000000000000000001011010 $
1-
b0000000000000000000000000000000000000000000000000000000001011010 .
#92500
0#
0-
#93000
1#
b0000000000000000000000000000000000000000000000000000000001011011 $
1-
b0000000000000000000000000000000000000000000000000000000001011011 .
#93500
0#
0-
#94000
1#
b0000000000000000000000000000000000000000000000000000000001011100 $
1-
b0000000000000000000000000000000000000000000000000000000001011100 .
#94500
0#
0-
#95000
1#
b0000000000000000000000000000000000000000000000000000000001011101 $
1-
b0000000000000000000000000000000000000000000000000000000001011101 .
#95500
0#
0-
#96000
1#
b0000000000000000000000000000000000000000000000000000000001011110 $
1-
b0000000000000000000000000000000000000000000000000000000001011110 .
#96500
0#
0-
#97000
1#
b0000000000000000000000000000000000000000000000000000000001011111 $
1-
b0000000000000000000000000000000000000000000000000000000001011111 .
#97500
0#
0-
#98000
1#
b0000000000000000000000000000000000000000000000000000000001100000 $
1-
b0000000000000000000000000000000000000000000000000000000001100000 .
#98500
0#
0-
#99000
1#
b0000000000000000000000000000000000000000000000000000000001100001 $
1-
b0000000000000000000000000000000000000000000000000000000001100001 .
#99500
0#
0-
#100000
1#
b0000000000000000000000000000000000000000000000000000000001100010 $
1-
b0000000000000000000000000000000000000000000000000000000001100010 .
#100500
0#
0-
#101000
1#
b0000000000000000000000000000000000000000000000000000000001100011 $
1-
b0000000000000000000000000000000000000000000000000000000001100011 .
#101500
0#
0-
#102000
1#
b0000000000000000000000000000000000000000000000000000000001100100 $
1-
b0000000000000000000000000000000000000000000000000000000001100100 .
#102500
0#
0-
#103000
1#
b0000000000000000000000000000000000000000000000000000000001100101 $
1-
b0000000000000000000000000000000000000000000000000000000001100101 .
#103500
0#
0-
#104000
1#
b0000000000000000000000000000000000000000000000000000000001100110 $
1-
b0000000000000000000000000000000000000000000000000000000001100110 .
#104500
0#
0-
#105000
1#
b0000000000000000000000000000000000000000000000000000000001100111 $
1-
b0000000000000000000000000000000000000000000000000000000001100111 .
#105500
0#
0-
#106000
1#
b0000000000000000000000000000000000000000000000000000000001101000 $
1-
b0000000000000000000000000000000000000000000000000000000001101000 .
#106500
0#
0-
#107000
1#
b0000000000000000000000000000000000000000000000000000000001101001 $
1-
b0000000000000000000000000000000000000000000000000000000001101001 .
#107500
0#
0-
#108000
1#
b0000000000000000000000000000000000000000000000000000000001101010 $
1-
b0000000000000000000000000000000000000000000000000000000001101010 .
#108500
0#
0-
#109000
1#
b0000000000000000000000000000000000000000000000000000000001101011 $
1-
b0000000000000000000000000000000000000000000000000000000001101011 .
#109500
0#
0-
#110000
1#
b0000000000000000000000000000000000000000000000000000000001101100 $
1-
b0000000000000000000000000000000000000000000000000000000001101100 .
#110500
0#
0-
#111000
1#
b0000000000000000000000000000000000000000000000000000000001101101 $
1-
b0000000000000000000000000000000000000000000000000000000001101101 .
#111500
0#
0-
#112000
1#
b0000000000000000000000000000000000000000000000000000000001101110 $
1-
b0000000000000000000000000000000000000000000000000000000001101110 .
#112500
0#
0-
#113000
1#
b0000000000000000000000000000000000000000000000000000000001101111 $
1-
b0000000000000000000000000000000000000000000000000000000001101111 .
#113500
0#
0-
#114000
1#
b0000000000000000000000000000000000000000000000000000000001110000 $
1-
b0000000000000000000000000000000000000000000000000000000001110000 .
#114500
0#
0-
#115000
1#
b0000000000000000000000000000000000000000000000000000000001110001 $
1-
b0000000000000000000000000000000000000000000000000000000001110001 .
#115500
0#
0-
#116000
1#
b0000000000000000000000000000000000000000000000000000000001110010 $
1-
b0000000000000000000000000000000000000000000000000000000001110010 .
#116500
0#
0-
#117000
1#
b0000000000000000000000000000000000000000000000000000000001110011 $
1-
b0000000000000000000000000000000000000000000000000000000001110011 .
#117500
0#
0-
#118000
1#
b0000000000000000000000000000000000000000000000000000000001110100 $
1-
b0000000000000000000000000000000000000000000000000000000001110100 .
#118500
0#
0-
#119000
1#
b0000000000000000000000000000000000000000000000000000000001110101 $
1-
b0000000000000000000000000000000000000000000000000000000001110101 .
#119500
0#
0-
#120000
1#
b0000000000000000000000000000000000000000000000000000000001110110 $
1-
b0000000000000000000000000000000000000000000000000000000001110110 .
#120500
0#
0-
#121000
1#
b0000000000000000000000000000000000000000000000000000000001110111 $
1-
b0000000000000000000000000000000000000000000000000000000001110111 .
#121500
0#
0-
#122000
1#
b0000000000000000000000000000000000000000000000000000000001111000 $
1-
b0000000000000000000000000000000000000000000000000000000001111000 .
#122500
0#
0-
#123000
1#
b0000000000000000000000000000000000000000000000000000000001111001 $
1-
b0000000000000000000000000000000000000000000000000000000001111001 .
#123500
0#
0-
#124000
1#
b0000000000000000000000000000000000000000000000000000000001111010 $
1-
b0000000000000000000000000000000000000000000000000000000001111010 .
#124500
0#
0-
#125000
1#
b0000000000000000000000000000000000000000000000000000000001111011 $
1-
b0000000000000000000000000000000000000000000000000000000001111011 .
#125500
0#
0-
#126000
1#
b0000000000000000000000000000000000000000000000000000000001111100 $
1-
b0000000000000000000000000000000000000000000000000000000001111100 .
#126500
0#
0-
#127000
1#
b0000000000000000000000000000000000000000000000000000000001111101 $
1-
b0000000000000000000000000000000000000000000000000000000001111101 .
#127500
0#
0-
#128000
1#
b0000000000000000000000000000000000000000000000000000000001111110 $
1-
b0000000000000000000000000000000000000000000000000000000001111110 .
#128500
0#
0-
#129000
1#
b0000000000000000000000000000000000000000000000000000000001111111 $
1-
b0000000000000000000000000000000000000000000000000000000001111111 .
#129500
0#
0-
#130000
1#
b0000000000000000000000000000000000000000000000000000000000000000 $
b1000000000001000000100110101010110000000000010000001001101010101 &
b11111111 (
b1000000000001000000100110101010110000000000010000001001101010101 +
1-
b0000000000000000000000000000000000000000000000000000000000000000 .
b1000000000001000000100110101010110000000000010000001001101010101 0
b11111111 2
b1000000000001000000100110101010110000000000010000001001101010101 5
b00000000000000000000000000001000 8
#130500
0#
0-
#131000
1#
1-
#131500
0#
0-
#132000
1#
b0000000000000000000000000000000000000000000000000000000000001000 $
b1100100110011100110110011001110111101001100111101010100110011010 &
1)
b0000000000000000000000000000000000000000000000000000000000000000 +
1-
b0000000000000000000000000000000000000000000000000000000000001000 .
b1100100110011100110110011001110111101001100111101010100110011010 0
13
b0000000000000000000000000000000000000000000000000000000000000000 5
#132500
0#
0-
#133000
1#
0)
b1100100110011100110110011001110111101001100111101010100110011010 +
1-
03
b1100100110011100110110011001110111101001100111101010100110011010 5
#133500
0#
0-
#134000
1#
1-
#134500
0#
0-
#135000
1#
b0000000000000000000000000000000000000000000000000000000000010000 $
b0010001001000010010101110100001000100010010000100101011101000010 &
1)
b0000000000000000000000000000000000000000000000000000000000000000 +
1-
b0000000000000000000000000000000000000000000000000000000000010000 .
b0010001001000010010101110100001000100010010000100101011101000010 0
13
b0000000000000000000000000000000000000000000000000000000000000000 5
#135500
0#
0-
#136000
1#
0)
b0010001001000010010101110100001000100010010000100101011101000010 +
1-
03
b0010001001000010010101110100001000100010010000100101011101000010 5
#136500
0#
0-
#137000
1#
1-
#137500
0#
0-
#138000
1#
b0000000000000000000000000000000000000000000000000000000000011000 $
b1000000010000110011001010000001010000000100001100110010100000010 &
1)
b0000000000000000000000000000000000000000000000000000000000000000 +
1-
b0000000000000000000000000000000000000000000000000000000000011000 .
b1000000010000110011001010000001010000000100001100110010100000010 0
13
b0000000000000000000000000000000000000000000000000000000000000000 5
#138500
0#
0-
#139000
1#
0)
b1000000010000110011001010000001010000000100001100110010100000010 +
1-
03
b1000000010000110011001010000001010000000100001100110010100000010 5
#139500
0#
0-
#140000
1#
1-
#140500
0#
0-
#141000
1#
1)
1-
13
#141500
0#
0-
#142000
1#
b0000000000000000000000000000000000000000000000000000000000000000 $
b0000000000000000000000000000000000000000000000000000000000000000 &
0)
0*
b1000000000001000000100110101010110000000000010000001001101010101 +
1-
b0000000000000000000000000000000000000000000000000000000000000000 .
b0000000000000000000000000000000000000000000000000000000000000000 0
03
04
b1000000000001000000100110101010110000000000010000001001101010101 5
#142500
0#
0-
#143000
1#
1*
b0000000000000000000000000000000000000000000000000000000000000000 +
1-
14
b0000000000000000000000000000000000000000000000000000000000000000 5
#143500
0#
0-
#144000
1#
1-
#144500
0#
0-
#145000
1#
b0000000000000000000000000000000000000000000000000000000000000001 $
1-
b0000000000000000000000000000000000000000000000000000000000000001 .
#145500
0#
0-
#146000
1#
b0000000000000000000000000000000000000000000000000000000000000010 $
1-
b0000000000000000000000000000000000000000000000000000000000000010 .
#146500
0#
0-
#147000
1#
b0000000000000000000000000000000000000000000000000000000000000011 $
1-
b0000000000000000000000000000000000000000000000000000000000000011 .
#147500
0#
0-
#148000
1#
b0000000000000000000000000000000000000000000000000000000000000100 $
1-
b0000000000000000000000000000000000000000000000000000000000000100 .
#148500
0#
0-
#149000
1#
b0000000000000000000000000000000000000000000000000000000000000101 $
1-
b0000000000000000000000000000000000000000000000000000000000000101 .
#149500
0#
0-
#150000
1#
b0000000000000000000000000000000000000000000000000000000000000110 $
1-
b0000000000000000000000000000000000000000000000000000000000000110 .
#150500
0#
0-
#151000
1#
b0000000000000000000000000000000000000000000000000000000000000111 $
1-
b0000000000000000000000000000000000000000000000000000000000000111 .
#151500
0#
0-
#152000
1#
b0000000000000000000000000000000000000000000000000000000000001000 $
1-
b0000000000000000000000000000000000000000000000000000000000001000 .
#152500
0#
0-
#153000
1#
b0000000000000000000000000000000000000000000000000000000000001001 $
1-
b0000000000000000000000000000000000000000000000000000000000001001 .
#153500
0#
0-
#154000
1#
b0000000000000000000000000000000000000000000000000000000000001010 $
1-
b0000000000000000000000000000000000000000000000000000000000001010 .
#154500
0#
0-
#155000
1#
b0000000000000000000000000000000000000000000000000000000000001011 $
1-
b0000000000000000000000000000000000000000000000000000000000001011 .
#155500
0#
0-
#156000
1#
b0000000000000000000000000000000000000000000000000000000000001100 $
1-
b0000000000000000000000000000000000000000000000000000000000001100 .
#156500
0#
0-
#157000
1#
b0000000000000000000000000000000000000000000000000000000000001101 $
1-
b0000000000000000000000000000000000000000000000000000000000001101 .
#157500
0#
0-
#158000
1#
b0000000000000000000000000000000000000000000000000000000000001110 $
1-
b0000000000000000000000000000000000000000000000000000000000001110 .
#158500
0#
0-
#159000
1#
b0000000000000000000000000000000000000000000000000000000000001111 $
1-
b0000000000000000000000000000000000000000000000000000000000001111 .
#159500
0#
0-
#160000
1#
b0000000000000000000000000000000000000000000000000000000000010000 $
1-
b0000000000000000000000000000000000000000000000000000000000010000 .
#160500
0#
0-
#161000
1#
b0000000000000000000000000000000000000000000000000000000000010001 $
1-
b0000000000000000000000000000000000000000000000000000000000010001 .
#161500
0#
0-
#162000
1#
b0000000000000000000000000000000000000000000000000000000000010010 $
1-
b0000000000000000000000000000000000000000000000000000000000010010 .
#162500
0#
0-
#163000
1#
b0000000000000000000000000000000000000000000000000000000000010011 $
1-
b0000000000000000000000000000000000000000000000000000000000010011 .
#163500
0#
0-
#164000
1#
b0000000000000000000000000000000000000000000000000000000000010100 $
1-
b0000000000000000000000000000000000000000000000000000000000010100 .
#164500
0#
0-
#165000
1#
b0000000000000000000000000000000000000000000000000000000000010101 $
1-
b0000000000000000000000000000000000000000000000000000000000010101 .
#165500
0#
0-
#166000
1#
b0000000000000000000000000000000000000000000000000000000000010110 $
1-
b0000000000000000000000000000000000000000000000000000000000010110 .
#166500
0#
0-
#167000
1#
b0000000000000000000000000000000000000000000000000000000000010111 $
1-
b0000000000000000000000000000000000000000000000000000000000010111 .
#167500
0#
0-
#168000
1#
b0000000000000000000000000000000000000000000000000000000000011000 $
1-
b0000000000000000000000000000000000000000000000000000000000011000 .
#168500
0#
0-
#169000
1#
b0000000000000000000000000000000000000000000000000000000000011001 $
1-
b0000000000000000000000000000000000000000000000000000000000011001 .
#169500
0#
0-
#170000
1#
b0000000000000000000000000000000000000000000000000000000000011010 $
1-
b0000000000000000000000000000000000000000000000000000000000011010 .
#170500
0#
0-
#171000
1#
b0000000000000000000000000000000000000000000000000000000000011011 $
1-
b0000000000000000000000000000000000000000000000000000000000011011 .
#171500
0#
0-
#172000
1#
b0000000000000000000000000000000000000000000000000000000000011100 $
1-
b0000000000000000000000000000000000000000000000000000000000011100 .
#172500
0#
0-
#173000
1#
b0000000000000000000000000000000000000000000000000000000000011101 $
1-
b0000000000000000000000000000000000000000000000000000000000011101 .
#173500
0#
0-
#174000
1#
b0000000000000000000000000000000000000000000000000000000000011110 $
1-
b0000000000000000000000000000000000000000000000000000000000011110 .
#174500
0#
0-
#175000
1#
b0000000000000000000000000000000000000000000000000000000000011111 $
1-
b0000000000000000000000000000000000000000000000000000000000011111 .
#175500
0#
0-
#176000
1#
b0000000000000000000000000000000000000000000000000000000000100000 $
1-
b0000000000000000000000000000000000000000000000000000000000100000 .
#176500
0#
0-
#177000
1#
b0000000000000000000000000000000000000000000000000000000000100001 $
1-
b0000000000000000000000000000000000000000000000000000000000100001 .
#177500
0#
0-
#178000
1#
b0000000000000000000000000000000000000000000000000000000000100010 $
1-
b0000000000000000000000000000000000000000000000000000000000100010 .
#178500
0#
0-
#179000
1#
b0000000000000000000000000000000000000000000000000000000000100011 $
1-
b0000000000000000000000000000000000000000000000000000000000100011 .
#179500
0#
0-
#180000
1#
b0000000000000000000000000000000000000000000000000000000000100100 $
1-
b0000000000000000000000000000000000000000000000000000000000100100 .
#180500
0#
0-
#181000
1#
b0000000000000000000000000000000000000000000000000000000000100101 $
1-
b0000000000000000000000000000000000000000000000000000000000100101 .
#181500
0#
0-
#182000
1#
b0000000000000000000000000000000000000000000000000000000000100110 $
1-
b0000000000000000000000000000000000000000000000000000000000100110 .
#182500
0#
0-
#183000
1#
b0000000000000000000000000000000000000000000000000000000000100111 $
1-
b0000000000000000000000000000000000000000000000000000000000100111 .
#183500
0#
0-
#184000
1#
b0000000000000000000000000000000000000000000000000000000000101000 $
1-
b0000000000000000000000000000000000000000000000000000000000101000 .
#184500
0#
0-
#185000
1#
b0000000000000000000000000000000000000000000000000000000000101001 $
1-
b0000000000000000000000000000000000000000000000000000000000101001 .
#185500
0#
0-
#186000
1#
b0000000000000000000000000000000000000000000000000000000000101010 $
1-
b0000000000000000000000000000000000000000000000000000000000101010 .
#186500
0#
0-
#187000
1#
b0000000000000000000000000000000000000000000000000000000000101011 $
1-
b0000000000000000000000000000000000000000000000000000000000101011 .
#187500
0#
0-
