regfile.sv
// regfile.sv

module regfile (
    // basic signals
    input logic clk,
    input logic rst_n,

    // Reads
    input logic [7:0] address1,
    input logic [7:0] address2,
    output logic [63:0] read_data1,
    output logic [63:0] read_data2,

    // Writes
    input logic write_enable,
    input logic [63:0] write_data,
    input logic [7:0] address3
);

// 64-bit register, 256 of them (addressed with 8 bits)
reg [63:0] registers [0:255];

// Write logic
always @(posedge clk) begin
    // reset support, init to 0
    if(rst_n == 1'b0) begin
        for(int i=0; i<256; i++) begin
            registers[i] <= 64'b0;
        end
    end
    // Write, except on 0, reserved for a zero constant according to ZEAL specs
    else if(write_enable == 1'b1 && address3 != 0) begin
        registers[address3] <= write_data;
    end
end

// Read logic, async
always_comb begin : readLogic
    read_data1 = registers[address1];
    read_data2 = registers[address2];
end

endmodule

regfile/dump.vcd
$version Generated by VerilatedVcd $end
$timescale 1ps $end
 $scope module $rootio $end
  $var wire 1 # clk $end
  $var wire 1 $ rst_n $end
  $var wire 8 % address1 [7:0] $end
  $var wire 8 & address2 [7:0] $end
  $var wire 64 ' read_data1 [63:0] $end
  $var wire 64 ) read_data2 [63:0] $end
  $var wire 1 + write_enable $end
  $var wire 64 , write_data [63:0] $end
  $var wire 8 . address3 [7:0] $end
 $upscope $end
 $scope module regfile $end
  $var wire 1 / clk $end
  $var wire 1 0 rst_n $end
  $var wire 8 1 address1 [7:0] $end
  $var wire 8 2 address2 [7:0] $end
  $var wire 64 3 read_data1 [63:0] $end
  $var wire 64 5 read_data2 [63:0] $end
  $var wire 1 7 write_enable $end
  $var wire 64 8 write_data [63:0] $end
  $var wire 8 : address3 [7:0] $end
  $scope module unnamedblk1 $end
   $var wire 32 ; i [31:0] $end
  $upscope $end
 $upscope $end
$enddefinitions $end


#0
1#
0$
b00000000 %
b00000000 &
b0000000000000000000000000000000000000000000000000000000000000000 '
b0000000000000000000000000000000000000000000000000000000000000000 )
0+
b0000000000000000000000000000000000000000000000000000000000000000 ,
b00000000 .
1/
00
b00000000 1
b00000000 2
b0000000000000000000000000000000000000000000000000000000000000000 3
b0000000000000000000000000000000000000000000000000000000000000000 5
07
b0000000000000000000000000000000000000000000000000000000000000000 8
b00000000 :
b00000000000000000000000100000000 ;
#5000
0#
0/
#10000
1#
1$
1/
10
#15000
0#
0/
#20000
1#
1/
#21000
b00010100 %
b11001001 &
b00010100 1
b11001001 2
#22000
1+
b1011110001101111100101101011011100001010111001101011100001010011 ,
b10110010 .
17
b1011110001101111100101101011011100001010111001101011100001010011 8
b10110010 :
#25000
0#
0/
#30000
1#
0+
1/
07
#32000
b11101111 %
b01110000 &
b11101111 1
b01110000 2
#33000
1+
b0011001100100010101001101001011100001101010000010000011100101000 ,
b11110010 .
17
b0011001100100010101001101001011100001101010000010000011100101000 8
b11110010 :
#35000
0#
0/
#40000
1#
0+
1/
07
#42000
b11001100 %
b10100010 &
b11001100 1
b10100010 2
#43000
1+
b1100100111001101001111100011101101100010100100110100000010101101 ,
b11100111 .
17
b1100100111001101001111100011101101100010100100110100000010101101 8
b11100111 :
#45000
0#
0/
#50000
1#
0+
1/
07
#52000
b00100111 %
b11010101 &
b00100111 1
b11010101 2
#53000
1+
b0111101000110010110110001100100110001000110001111000110111000101 ,
b00000110 .
17
b0111101000110010110110001100100110001000110001111000110111000101 8
b00000110 :
#55000
0#
0/
#60000
1#
0+
1/
07
#62000
b00011111 %
b01111001 &
b00011111 1
b01111001 2
#63000
1+
b1011100111010011110011111110100011000000010101111010001111110111 ,
b01000100 .
17
b1011100111010011110011111110100011000000010101111010001111110111 8
b01000100 :
#65000
0#
0/
#70000
1#
0+
1/
07
#72000
b11101100 %
b11111000 &
b11101100 1
b11111000 2
#73000
1+
b1101010000110111101111100010110110011100100101100111011101011011 ,
b10100010 .
17
b1101010000110111101111100010110110011100100101100111011101011011 8
b10100010 :
#75000
0#
0/
#80000
1#
0+
1/
07
#82000
b10100011 %
b11111001 &
b10100011 1
b11111001 2
#83000
1+
b1100110101101100100000010011000110011010001111110111010100111100 ,
b01010101 .
17
b1100110101101100100000010011000110011010001111110111010100111100 8
b01010101 :
#85000
0#
0/
#90000
1#
0+
1/
07
#92000
b10110111 %
b01110001 &
b10110111 1
b01110001 2
#93000
1+
b1000110001101001110011101111000110110110001011110101010011111001 ,
b11010001 .
17
b1000110001101001110011101111000110110110001011110101010011111001 8
b11010001 :
#95000
0#
0/
#100000
1#
0+
1/
07
#102000
b00001000 %
b00111010 &
b00001000 1
b00111010 2
#103000
1+
b1111110111011000000110100000011010110101111010101000110110000011 ,
b11011100 .
17
b1111110111011000000110100000011010110101111010101000110110000011 8
b11011100 :
#105000
0#
0/
#110000
1#
0+
1/
07
#112000
b11110000 %
b00010011 &
b11110000 1
b00010011 2
#113000
1+
b0110101011110110011110000000100010011011011101010011110011110010 ,
b10101111 .
17
b0110101011110110011110000000100010011011011101010011110011110010 8
b10101111 :
#115000
0#
0/
#120000
1#
0+
1/
07
#122000
b11010000 %
b01110001 &
b11010000 1
b01110001 2
#123000
1+
b0011101111101101001111001010100011100101001010111010010000111010 ,
b00111111 .
17
b0011101111101101001111001010100011100101001010111010010000111010 8
b00111111 :
#125000
0#
0/
#130000
1#
0+
1/
07
#132000
b10011000 %
b01010000 &
b10011000 1
b01010000 2
#133000
1+
b1010010001101100010011111101110101010101100110110001011101111111 ,
b00111010 .
17
b1010010001101100010011111101110101010101100110110001011101111111 8
b00111010 :
#135000
0#
0/
#140000
1#
0+
1/
07
#142000
b01100001 %
b11111001 &
b01100001 1
b11111001 2
#143000
1+
b1101000011111010011111000001101011111010101011011100100010100101 ,
b00000011 .
17
b1101000011111010011111000001101011111010101011011100100010100101 8
b00000011 :
#145000
0#
0/
#150000
1#
0+
1/
07
#152000
b01001100 %
b01110001 &
b01001100 1
b01110001 2
#153000
1+
b0011101101100111101111001001010110101101101011001110101101001010 ,
b10001001 .
17
b0011101101100111101111001001010110101101101011001110101101001010 8
b10001001 :
#155000
0#
0/
#160000
1#
0+
1/
07
#162000
b01110011 %
b00000101 &
b01110011 1
b00000101 2
#163000
1+
b0101111101001001001101001111010111000000011100001010000110111001 ,
b01100011 .
17
b0101111101001001001101001111010111000000011100001010000110111001 8
b01100011 :
#165000
0#
0/
#170000
1#
0+
1/
07
#172000
b10110111 %
b11110111 &
b10110111 1
b11110111 2
#173000
1+
b1000111011010001101000111110100100000100111101010111100001001001 ,
b00110010 .
17
b1000111011010001101000111110100100000100111101010111100001001001 8
b00110010 :
#175000
0#
0/
#180000
1#
0+
1/
07
#182000
b01010011 %
b10001000 &
b01010011 1
b10001000 2
#183000
1+
b0110110010110010110111110001000100010011110101100000001000001110 ,
b01011111 .
17
b0110110010110010110111110001000100010011110101100000001000001110 8
b01011111 :
#185000
0#
0/
#190000
1#
0+
1/
07
#192000
b11111100 %
b01110101 &
b11111100 1
b01110101 2
#193000
1+
b0110001101111100011100000000011100000101010011011011001011111010 ,
b11010000 .
17
b0110001101111100011100000000011100000101010011011011001011111010 8
b11010000 :
#195000
0#
0/
#200000
1#
0+
1/
07
#202000
b11100111 %
b00010011 &
b1100100111001101001111100011101101100010100100110100000010101101 '
b11100111 1
b00010011 2
b1100100111001101001111100011101101100010100100110100000010101101 3
#203000
1+
b1101111101110001111010101110010001000010000000001110010100100001 ,
b10110100 .
17
b1101111101110001111010101110010001000010000000001110010100100001 8
b10110100 :
#205000
0#
0/
#210000
1#
0+
1/
07
#212000
b11001000 %
b00100110 &
b0000000000000000000000000000000000000000000000000000000000000000 '
b11001000 1
b00100110 2
b0000000000000000000000000000000000000000000000000000000000000000 3
#213000
1+
b1011010111101100111110100100110100101010010010001011011110001000 ,
b11010110 .
17
b1011010111101100111110100100110100101010010010001011011110001000 8
b11010110 :
#215000
0#
0/
#220000
1#
0+
1/
07
#222000
b01001101 %
b01010100 &
b01001101 1
b01010100 2
#223000
1+
b0011111000111001110100011000010101001010010100011110101110010010 ,
b00100111 .
17
b0011111000111001110100011000010101001010010100011110101110010010 8
b00100111 :
#225000
0#
0/
#230000
1#
0+
1/
07
#232000
b00001111 %
b00100001 &
b00001111 1
b00100001 2
#233000
1+
b1101101010111101011111011001110100100010011101111100110111000001 ,
b00110000 .
17
b1101101010111101011111011001110100100010011101111100110111000001 8
b00110000 :
#235000
0#
0/
#240000
1#
0+
1/
07
#242000
b10110010 %
b11010100 &
b1011110001101111100101101011011100001010111001101011100001010011 '
b10110010 1
b11010100 2
b1011110001101111100101101011011100001010111001101011100001010011 3
#243000
1+
b1101110101100001101001011111000100101111011111011011001010100000 ,
b01011100 .
17
b1101110101100001101001011111000100101111011111011011001010100000 8
b01011100 :
#245000
0#
0/
#250000
1#
0+
1/
07
#252000
b01111110 %
b00111101 &
b0000000000000000000000000000000000000000000000000000000000000000 '
b01111110 1
b00111101 2
b0000000000000000000000000000000000000000000000000000000000000000 3
#253000
1+
b1010101110000010111110011001110001010010001111101010000000001011 ,
b10111100 .
17
b1010101110000010111110011001110001010010001111101010000000001011 8
b10111100 :
#255000
0#
0/
#260000
1#
0+
1/
07
#262000
b00101010 %
b10100000 &
b00101010 1
b10100000 2
#263000
1+
b0000110000001001110000111100111000101011001101111000010110000100 ,
b11011000 .
17
b0000110000001001110000111100111000101011001101111000010110000100 8
b11011000 :
#265000
0#
0/
#270000
1#
0+
1/
07
#272000
b11101001 %
b00010100 &
b11101001 1
b00010100 2
#273000
1+
b0110011011110111001110000000011011011111010010101100010000000001 ,
b00010000 .
17
b0110011011110111001110000000011011011111010010101100010000000001 8
b00010000 :
#275000
0#
0/
#280000
1#
0+
1/
07
#282000
b11110111 %
b00011110 &
b11110111 1
b00011110 2
#283000
1+
b1000101101011100100000000100110010110111100100000111001011011111 ,
b10000000 .
17
b1000101101011100100000000100110010110111100100000111001011011111 8
b10000000 :
#285000
0#
0/
#290000
1#
0+
1/
07
#292000
b10101111 %
b11100100 &
b0110101011110110011110000000100010011011011101010011110011110010 '
b10101111 1
b11100100 2
b0110101011110110011110000000100010011011011101010011110011110010 3
#293000
1+
b1111010111010001010011110101101001011001001011111010010000000101 ,
b11111001 .
17
b1111010111010001010011110101101001011001001011111010010000000101 8
b11111001 :
#295000
0#
0/
#300000
1#
0+
1/
07
#302000
b10001111 %
b00011001 &
b0000000000000000000000000000000000000000000000000000000000000000 '
b10001111 1
b00011001 2
b0000000000000000000000000000000000000000000000000000000000000000 3
#303000
1+
b0011001010101011011111110111010100100011011111000001011011110011 ,
b00001101 .
17
b0011001010101011011111110111010100100011011111000001011011110011 8
b00001101 :
#305000
0#
0/
#310000
1#
0+
1/
07
#312000
b00111001 %
b01110101 &
b00111001 1
b01110101 2
#313000
1+
b0011010100001111011100011111011111101000100100011010100001111010 ,
b00101110 .
17
b0011010100001111011100011111011111101000100100011010100001111010 8
b00101110 :
#315000
0#
0/
#320000
1#
0+
1/
07
#322000
b01011100 %
b11101001 &
b1101110101100001101001011111000100101111011111011011001010100000 '
b01011100 1
b11101001 2
b1101110101100001101001011111000100101111011111011011001010100000 3
#323000
1+
b1111100111010011100010011101001000011010111000001101100100001100 ,
b11101110 .
17
b1111100111010011100010011101001000011010111000001101100100001100 8
b11101110 :
#325000
0#
0/
#330000
1#
0+
1/
07
#332000
b10000111 %
b11101011 &
b0000000000000000000000000000000000000000000000000000000000000000 '
b10000111 1
b11101011 2
b0000000000000000000000000000000000000000000000000000000000000000 3
#333000
1+
b1000001101000111100011110001111110111010010001011111110111011111 ,
b10110101 .
17
b1000001101000111100011110001111110111010010001011111110111011111 8
b10110101 :
#335000
0#
0/
#340000
1#
0+
1/
07
#342000
b10000110 %
b00100111 &
b0011111000111001110100011000010101001010010100011110101110010010 )
b10000110 1
b00100111 2
b0011111000111001110100011000010101001010010100011110101110010010 5
#343000
1+
b0101111011010000111001111001001110100101000110011111010100111111 ,
b10110111 .
17
b0101111011010000111001111001001110100101000110011111010100111111 8
b10110111 :
#345000
0#
0/
#350000
1#
0+
1/
07
#352000
b10001000 %
b11100100 &
b0000000000000000000000000000000000000000000000000000000000000000 )
b10001000 1
b11100100 2
b0000000000000000000000000000000000000000000000000000000000000000 5
#353000
1+
b0111010100000011001110101011001001111010011101001011010100101101 ,
b11101101 .
17
b0111010100000011001110101011001001111010011101001011010100101101 8
b11101101 :
#355000
0#
0/
#360000
1#
0+
1/
07
#362000
b01101000 %
b01100110 &
b01101000 1
b01100110 2
#363000
1+
b1101110101101100110001000101000001110000100011000101000100111001 ,
b11000110 .
17
b1101110101101100110001000101000001110000100011000101000100111001 8
b11000110 :
#365000
0#
0/
#370000
1#
0+
1/
07
#372000
b01110010 %
b11001110 &
b01110010 1
b11001110 2
#373000
1+
b0010101011011010110001110000111000110010110011011010100110001001 ,
b11111111 .
17
b0010101011011010110001110000111000110010110011011010100110001001 8
b11111111 :
#375000
0#
0/
#380000
1#
0+
1/
07
#382000
b01111101 %
b01101111 &
b01111101 1
b01101111 2
#383000
1+
b0110010001001110001010000100010010000000011110110100101100101001 ,
b01001100 .
17
b0110010001001110001010000100010010000000011110110100101100101001 8
b01001100 :
#385000
0#
0/
#390000
1#
0+
1/
07
#392000
b01100110 %
b10010010 &
b01100110 1
b10010010 2
#393000
1+
b1001111111000001100001000011110001110011010110010110110111111111 ,
b10011111 .
17
b1001111111000001100001000011110001110011010110010110110111111111 8
b10011111 :
#395000
0#
0/
#400000
1#
0+
1/
07
#402000
b00111000 %
b00001010 &
b00111000 1
b00001010 2
#403000
1+
b1100000111100100100001100110111110110010010011110110000110011111 ,
b10011100 .
17
b1100000111100100100001100110111110110010010011110110000110011111 8
b10011100 :
#405000
0#
0/
#410000
1#
0+
1/
07
#412000
b01000000 %
b00101010 &
b01000000 1
b00101010 2
#413000
1+
b1111011111011111101000011010101000001010110011100011101111000100 ,
b01101101 .
17
b1111011111011111101000011010101000001010110011100011101111000100 8
b01101101 :
#415000
0#
0/
#420000
1#
0+
1/
07
#422000
b01111000 %
b00101001 &
b01111000 1
b00101001 2
#423000
1+
b0011011101011110110001100101001001100010000010010001000010110100 ,
b01000000 .
17
b0011011101011110110001100101001001100010000010010001000010110100 8
b01000000 :
#425000
0#
0/
#430000
1#
0+
1/
07
#432000
b00010110 %
b01010110 &
b00010110 1
b01010110 2
#433000
1+
b0000000100111011110010111010110100100101001011101111010000010101 ,
b10110010 .
17
b0000000100111011110010111010110100100101001011101111010000010101 8
b10110010 :
#435000
0#
0/
#440000
1#
0+
1/
07
#442000
b10111010 %
b01110011 &
b10111010 1
b01110011 2
#443000
1+
b1010011101000010111010001100010100010111101111100011100011111010 ,
b10110001 .
17
b1010011101000010111010001100010100010111101111100011100011111010 8
b10110001 :
#445000
0#
0/
#450000
1#
0+
1/
07
#452000
b10111011 %
b10100010 &
b1101010000110111101111100010110110011100100101100111011101011011 )
b10111011 1
b10100010 2
b1101010000110111101111100010110110011100100101100111011101011011 5
#453000
1+
b0000111000110011100001100011110001000000111000001011010001001011 ,
b00000011 .
17
b0000111000110011100001100011110001000000111000001011010001001011 8
b00000011 :
#455000
0#
0/
#460000
1#
0+
1/
07
#462000
b00000001 %
b10111000 &
b0000000000000000000000000000000000000000000000000000000000000000 )
b00000001 1
b10111000 2
b0000000000000000000000000000000000000000000000000000000000000000 5
#463000
1+
b1000111110111001001101111000010001010101010101110110011011110111 ,
b11011111 .
17
b1000111110111001001101111000010001010101010101110110011011110111 8
b11011111 :
#465000
0#
0/
#470000
1#
0+
1/
07
#472000
b10011111 %
b00011111 &
b1001111111000001100001000011110001110011010110010110110111111111 '
b10011111 1
b00011111 2
b1001111111000001100001000011110001110011010110010110110111111111 3
#473000
1+
b0010010000000000100010001111000011111010101001001111010011100010 ,
b11001111 .
17
b0010010000000000100010001111000011111010101001001111010011100010 8
b11001111 :
#475000
0#
0/
#480000
1#
0+
1/
07
#482000
b00011011 %
b00001110 &
b0000000000000000000000000000000000000000000000000000000000000000 '
b00011011 1
b00001110 2
b0000000000000000000000000000000000000000000000000000000000000000 3
#483000
1+
b1111110100111011100010110000110001011101101000000010010100111100 ,
b01100100 .
17
b1111110100111011100010110000110001011101101000000010010100111100 8
b01100100 :
#485000
0#
0/
#490000
1#
0+
1/
07
#492000
b01110010 %
b10111001 &
b01110010 1
b10111001 2
#493000
1+
b0110101101001010101110010111001110001101110101000011100110111100 ,
b11011010 .
17
b0110101101001010101110010111001110001101110101000011100110111100 8
b11011010 :
#495000
0#
0/
#500000
1#
0+
1/
07
#502000
b00100010 %
b01001100 &
b0110010001001110001010000100010010000000011110110100101100101001 )
b00100010 1
b01001100 2
b0110010001001110001010000100010010000000011110110100101100101001 5
#503000
1+
b1110001110010010101011101100111011000101101100110110010010101011 ,
b01101000 .
17
b1110001110010010101011101100111011000101101100110110010010101011 8
b01101000 :
#505000
0#
0/
#510000
1#
0+
1/
07
#512000
b10100111 %
b10010011 &
b0000000000000000000000000000000000000000000000000000000000000000 )
b10100111 1
b10010011 2
b0000000000000000000000000000000000000000000000000000000000000000 5
#513000
1+
b1101111110110001100011110111110111001100101010100010001011111000 ,
b01110001 .
17
b1101111110110001100011110111110111001100101010100010001011111000 8
b01110001 :
#515000
0#
0/
#520000
1#
0+
1/
07
#522000
b10110110 %
b01010101 &
b1100110101101100100000010011000110011010001111110111010100111100 )
b10110110 1
b01010101 2
b1100110101101100100000010011000110011010001111110111010100111100 5
#523000
1+
b1110110101001101110110001110010001010010001110000100111011101111 ,
b01011000 .
17
b1110110101001101110110001110010001010010001110000100111011101111 8
b01011000 :
#525000
0#
0/
#530000
1#
0+
1/
07
#532000
b11101001 %
b10110100 &
b1101111101110001111010101110010001000010000000001110010100100001 )
b11101001 1
b10110100 2
b1101111101110001111010101110010001000010000000001110010100100001 5
#533000
1+
b0010110110101001100100101101111101011011110000100110111000100010 ,
b00011101 .
17
b0010110110101001100100101101111101011011110000100110111000100010 8
b00011101 :
#535000
0#
0/
#540000
1#
0+
1/
07
#542000
b01111111 %
b00000011 &
b0000111000110011100001100011110001000000111000001011010001001011 )
b01111111 1
b00000011 2
b0000111000110011100001100011110001000000111000001011010001001011 5
#543000
1+
b0101011000110011100001010110101010001011100000110100011101101100 ,
b01000110 .
17
b0101011000110011100001010110101010001011100000110100011101101100 8
b01000110 :
#545000
0#
0/
#550000
1#
0+
1/
07
#552000
b01101001 %
b00110001 &
b0000000000000000000000000000000000000000000000000000000000000000 )
b01101001 1
b00110001 2
b0000000000000000000000000000000000000000000000000000000000000000 5
#553000
1+
b1110101001101000011100110001111111001011110101001100111010001001 ,
b11110101 .
17
b1110101001101000011100110001111111001011110101001100111010001001 8
b11110101 :
#555000
0#
0/
#560000
1#
0+
1/
07
#562000
b00011110 %
b01000101 &
b00011110 1
b01000101 2
#563000
1+
b0001011111110111100011110001000111100011001100000100001001001101 ,
b00010100 .
17
b0001011111110111100011110001000111100011001100000100001001001101 8
b00010100 :
#565000
0#
0/
#570000
1#
0+
1/
07
#572000
b00100011 %
b00100011 &
b00100011 1
b00100011 2
#573000
1+
b0100101000011011100111001100111110110001001101000100001110001100 ,
b10101000 .
17
b0100101000011011100111001100111110110001001101000100001110001100 8
b10101000 :
#575000
0#
0/
#580000
1#
0+
1/
07
#582000
b00001101 %
b00101100 &
b0011001010101011011111110111010100100011011111000001011011110011 '
b00001101 1
b00101100 2
b0011001010101011011111110111010100100011011111000001011011110011 3
#583000
1+
b0100010001010110011101010010100101101110011010101111000001001101 ,
b01111100 .
17
b0100010001010110011101010010100101101110011010101111000001001101 8
b01111100 :
#585000
0#
0/
#590000
1#
0+
1/
07
#592000
b11101100 %
b01000101 &
b0000000000000000000000000000000000000000000000000000000000000000 '
b11101100 1
b01000101 2
b0000000000000000000000000000000000000000000000000000000000000000 3
#593000
1+
b1111101000100101100111100011101001110111001110101010100000100000 ,
b00001101 .
17
b1111101000100101100111100011101001110111001110101010100000100000 8
b00001101 :
#595000
0#
0/
#600000
1#
0+
1/
07
#602000
b11110001 %
b01010010 &
b11110001 1
b01010010 2
#603000
1+
b0110000011101010001110111011111101000001010010001011110111111000 ,
b01110000 .
17
b0110000011101010001110111011111101000001010010001011110111111000 8
b01110000 :
#605000
0#
0/
#610000
1#
0+
1/
07
#612000
b00000011 %
b01001001 &
b0000111000110011100001100011110001000000111000001011010001001011 '
b00000011 1
b01001001 2
b0000111000110011100001100011110001000000111000001011010001001011 3
#613000
1+
b1100101111110001001011110101001111111001101101111100100010111101 ,
b11010100 .
17
b1100101111110001001011110101001111111001101101111100100010111101 8
b11010100 :
#615000
0#
0/
#620000
1#
0+
1/
07
#622000
b00111001 %
b00001101 &
b0000000000000000000000000000000000000000000000000000000000000000 '
b1111101000100101100111100011101001110111001110101010100000100000 )
b00111001 1
b00001101 2
b0000000000000000000000000000000000000000000000000000000000000000 3
b1111101000100101100111100011101001110111001110101010100000100000 5
#623000
1+
b0000010011101011000110001011101000110100101111000100110110000011 ,
b11011100 .
17
b0000010011101011000110001011101000110100101111000100110110000011 8
b11011100 :
#625000
0#
0/
#630000
1#
0+
1/
07
#632000
b11100111 %
b10011101 &
b1100100111001101001111100011101101100010100100110100000010101101 '
b0000000000000000000000000000000000000000000000000000000000000000 )
b11100111 1
b10011101 2
b1100100111001101001111100011101101100010100100110100000010101101 3
b0000000000000000000000000000000000000000000000000000000000000000 5
#633000
1+
b1110100011001011111111011010000100001101010001011010101101000000 ,
b11001111 .
17
b1110100011001011111111011010000100001101010001011010101101000000 8
b11001111 :
#635000
0#
0/
#640000
1#
0+
1/
07
#642000
b00011110 %
b01001110 &
b0000000000000000000000000000000000000000000000000000000000000000 '
b00011110 1
b01001110 2
b0000000000000000000000000000000000000000000000000000000000000000 3
#643000
1+
b1110110001011100100101011010001111001001111000000000101010001011 ,
b11011000 .
17
b1110110001011100100101011010001111001001111000000000101010001011 8
b11011000 :
#645000
0#
0/
#650000
1#
0+
1/
07
#652000
b11011011 %
b00101000 &
b11011011 1
b00101000 2
#653000
1+
b0011010011110110000010110110110110101000000110010001001100000111 ,
b00010101 .
17
b0011010011110110000010110110110110101000000110010001001100000111 8
b00010101 :
#655000
0#
0/
#660000
1#
0+
1/
07
#662000
b00000110 %
b11010000 &
b0111101000110010110110001100100110001000110001111000110111000101 '
b0110001101111100011100000000011100000101010011011011001011111010 )
b00000110 1
b11010000 2
b0111101000110010110110001100100110001000110001111000110111000101 3
b0110001101111100011100000000011100000101010011011011001011111010 5
#663000
1+
b0101010111001100100001101001110101110010010100000011101011100011 ,
b01100100 .
17
b0101010111001100100001101001110101110010010100000011101011100011 8
b01100100 :
#665000
0#
0/
#670000
1#
0+
1/
07
#672000
b01011101 %
b11100000 &
b0000000000000000000000000000000000000000000000000000000000000000 '
b0000000000000000000000000000000000000000000000000000000000000000 )
b01011101 1
b11100000 2
b0000000000000000000000000000000000000000000000000000000000000000 3
b0000000000000000000000000000000000000000000000000000000000000000 5
#673000
1+
b0001111101011100111101101110101010011000101111110101110111110010 ,
b10111010 .
17
b0001111101011100111101101110101010011000101111110101110111110010 8
b10111010 :
#675000
0#
0/
#680000
1#
0+
1/
07
#682000
b11101011 %
b00101001 &
b11101011 1
b00101001 2
#683000
1+
b0110100101111101010110100011101111010010111100000001100010100110 ,
b11110011 .
17
b0110100101111101010110100011101111010010111100000001100010100110 8
b11110011 :
#685000
0#
0/
#690000
1#
0+
1/
07
#692000
b00000111 %
b11011010 &
b0110101101001010101110010111001110001101110101000011100110111100 )
b00000111 1
b11011010 2
b0110101101001010101110010111001110001101110101000011100110111100 5
#693000
1+
b0100011000111110100000111100101110110011010111100100111010000111 ,
b10001101 .
17
b0100011000111110100000111100101110110011010111100100111010000111 8
b10001101 :
#695000
0#
0/
#700000
1#
0+
1/
07
#702000
b00001011 %
b11000100 &
b0000000000000000000000000000000000000000000000000000000000000000 )
b00001011 1
b11000100 2
b0000000000000000000000000000000000000000000000000000000000000000 5
#703000
1+
b1101000001100111110101111111011110110110001010011010010100011111 ,
b11110110 .
17
b1101000001100111110101111111011110110110001010011010010100011111 8
b11110110 :
#705000
0#
0/
#710000
1#
0+
1/
07
#712000
b00000110 %
b11110010 &
b0111101000110010110110001100100110001000110001111000110111000101 '
b0011001100100010101001101001011100001101010000010000011100101000 )
b00000110 1
b11110010 2
b0111101000110010110110001100100110001000110001111000110111000101 3
b0011001100100010101001101001011100001101010000010000011100101000 5
#713000
1+
b0100110100111011110010000010101000001110010010111110001101101111 ,
b00100000 .
17
b0100110100111011110010000010101000001110010010111110001101101111 8
b00100000 :
#715000
0#
0/
#720000
1#
0+
1/
07
#722000
b11100110 %
b01100110 &
b0000000000000000000000000000000000000000000000000000000000000000 '
b0000000000000000000000000000000000000000000000000000000000000000 )
b11100110 1
b01100110 2
b0000000000000000000000000000000000000000000000000000000000000000 3
b0000000000000000000000000000000000000000000000000000000000000000 5
#723000
1+
b0101101011111000110000110010000100000110110110011111100000011101 ,
b01101111 .
17
b0101101011111000110000110010000100000110110110011111100000011101 8
b01101111 :
#725000
0#
0/
#730000
1#
0+
1/
07
#732000
b01100000 %
b01101001 &
b01100000 1
b01101001 2
#733000
1+
b1101100110100110110011100111111010011110011011011001101010110001 ,
b01110100 .
17
b1101100110100110110011100111111010011110011011011001101010110001 8
b01110100 :
#735000
0#
0/
#740000
1#
0+
1/
07
#742000
b01000011 %
b10101101 &
b01000011 1
b10101101 2
#743000
1+
b0011000100110100001111111010001011111010100000010101000101000110 ,
b10101011 .
17
b0011000100110100001111111010001011111010100000010101000101000110 8
b10101011 :
#745000
0#
0/
#750000
1#
0+
1/
07
#752000
b01110101 %
b10100101 &
b01110101 1
b10100101 2
#753000
1+
b1100110010110011100101000010111110011101001111001110101010000011 ,
b00111001 .
17
b1100110010110011100101000010111110011101001111001110101010000011 8
b00111001 :
#755000
0#
0/
#760000
1#
0+
1/
07
#762000
b00011111 %
b00110000 &
b1101101010111101011111011001110100100010011101111100110111000001 )
b00011111 1
b00110000 2
b1101101010111101011111011001110100100010011101111100110111000001 5
#763000
1+
b1001000111111001000110101011001010000111011011111111100000100100 ,
b01100010 .
17
b1001000111111001000110101011001010000111011011111111100000100100 8
b01100010 :
#765000
0#
0/
#770000
1#
0+
1/
07
#772000
b11001111 %
b10001010 &
b1110100011001011111111011010000100001101010001011010101101000000 '
b0000000000000000000000000000000000000000000000000000000000000000 )
b11001111 1
b10001010 2
b1110100011001011111111011010000100001101010001011010101101000000 3
b0000000000000000000000000000000000000000000000000000000000000000 5
#773000
1+
b0011000100111110101011000011101000010001110001100111010011000000 ,
b00010110 .
17
b0011000100111110101011000011101000010001110001100111010011000000 8
b00010110 :
#775000
0#
0/
#780000
1#
0+
1/
07
#782000
b00010111 %
b01111111 &
b0000000000000000000000000000000000000000000000000000000000000000 '
b00010111 1
b01111111 2
b0000000000000000000000000000000000000000000000000000000000000000 3
#783000
1+
b1011011000101011010001110001111100100101010010110111110000011100 ,
b01101111 .
17
b1011011000101011010001110001111100100101010010110111110000011100 8
b01101111 :
#785000
0#
0/
#790000
1#
0+
1/
07
#792000
b01100000 %
b00010100 &
b0001011111110111100011110001000111100011001100000100001001001101 )
b01100000 1
b00010100 2
b0001011111110111100011110001000111100011001100000100001001001101 5
#793000
1+
b1000010111100110110001101010001100011101100111011111101011010101 ,
b01110000 .
17
b1000010111100110110001101010001100011101100111011111101011010101 8
b01110000 :
#795000
0#
0/
#800000
1#
0+
1/
07
#802000
b00011011 %
b11000110 &
b1101110101101100110001000101000001110000100011000101000100111001 )
b00011011 1
b11000110 2
b1101110101101100110001000101000001110000100011000101000100111001 5
#803000
1+
b1011101000001000000111010110001010111001111010001000100011110010 ,
b10101101 .
17
b1011101000001000000111010110001010111001111010001000100011110010 8
b10101101 :
#805000
0#
0/
#810000
1#
0+
1/
07
#812000
b00000010 %
b10101011 &
b0011000100110100001111111010001011111010100000010101000101000110 )
b00000010 1
b10101011 2
b0011000100110100001111111010001011111010100000010101000101000110 5
#813000
1+
b1011100110101001111000100111010001000101010000100110110111111100 ,
b00111100 .
17
b1011100110101001111000100111010001000101010000100110110111111100 8
b00111100 :
#815000
0#
0/
#820000
1#
0+
1/
07
#822000
b00011000 %
b01000011 &
b0000000000000000000000000000000000000000000000000000000000000000 )
b00011000 1
b01000011 2
b0000000000000000000000000000000000000000000000000000000000000000 5
#823000
1+
b1110111111100100111011011101001011011110000001101011100100101111 ,
b00111011 .
17
b1110111111100100111011011101001011011110000001101011100100101111 8
b00111011 :
#825000
0#
0/
#830000
1#
0+
1/
07
#832000
b01101000 %
b00100010 &
b1110001110010010101011101100111011000101101100110110010010101011 '
b01101000 1
b00100010 2
b1110001110010010101011101100111011000101101100110110010010101011 3
#833000
1+
b1001010001110111011110010100000010110001011011010001101000101101 ,
b10011110 .
17
b1001010001110111011110010100000010110001011011010001101000101101 8
b10011110 :
#835000
0#
0/
#840000
1#
0+
1/
07
#842000
b10010111 %
b10000011 &
b0000000000000000000000000000000000000000000000000000000000000000 '
b10010111 1
b10000011 2
b0000000000000000000000000000000000000000000000000000000000000000 3
#843000
1+
b0111101110010110110111001100110101011001010111011011011001111101 ,
b00000011 .
17
b0111101110010110110111001100110101011001010111011011011001111101 8
b00000011 :
#845000
0#
0/
#850000
1#
0+
1/
07
#852000
b11011000 %
b10101111 &
b1110110001011100100101011010001111001001111000000000101010001011 '
b0110101011110110011110000000100010011011011101010011110011110010 )
b11011000 1
b10101111 2
b1110110001011100100101011010001111001001111000000000101010001011 3
b0110101011110110011110000000100010011011011101010011110011110010 5
#853000
1+
b1000010111110110010101111111100011100000101001110011100010110101 ,
b10000000 .
17
b1000010111110110010101111111100011100000101001110011100010110101 8
b10000000 :
#855000
0#
0/
#860000
1#
0+
1/
07
