control/control.sv
module control (
//IN
input logic [15:0] op,
input logic [3:0] func4, //4-bit func4
input logic [7:0] func8, //we actually have 24-bits available but for now just use 8
//we use 8 because i've got no clue what I'd need that many more for and that's up
//to others to figure out. We already have 16-bit opcodes
input logic alu_zero,
input logic alu_last_bit,

//OUT
output logic [3:0] alu_control,
output logic [2:0] imm_source,
output logic mem_write,
output logic reg_write,
output logic alu_source,
output logic [1:0] write_back_source,
output logic pc_source,
output logic branch_inst, // ADDED TO DEAL WITH CHANGING DESTINATION TO R1 FOR BRANCH INSTRUCTIONS
output logic itype_src2_rs1, // Deal with I-type so ALU can use RS2
output logic [1:0] second_add_source
);

/**
* MAIN DECODER
*/

logic [1:0] alu_op;
logic branch;
logic jump;

always_comb begin
    case (op)
    //LW
    //16'b0000000000010000: begin //I decided to put the "load word" opcode as such because all zeros should be for the first ALU
    16'hB010: begin
        reg_write = 1'b1;
        imm_source = 3'b000;
        mem_write = 1'b0;
        alu_op = 2'b00;
        alu_source = 1'b1; // imm
        write_back_source = 2'b01; //memory_read
        branch = 1'b0;
        jump = 1'b0;
        itype_src2_rs1 = 1'b0;
        second_add_source = 2'b00;
    end
    // S-Type (SW)
    16'hC010: begin
      reg_write = 1'b0;
      imm_source = 3'b001;
      mem_write = 1'b1;
      alu_op = 2'b00;
      alu_source = 1'b1; // imm
      write_back_source = 2'b00;
      branch = 1'b0;
      jump = 1'b0;
      itype_src2_rs1 = 1'b0;
      second_add_source = 2'b00;
    end
    // R- Type (ADD, AND, OR, SUB, SLT, SLTU, XOR, SLL, SRL, SRAI, NE, SGT)
    16'hA000, 16'hA001, 16'hA002, 16'hA003, 16'hA004, 16'hA005, 16'hA006, 16'hA007, 16'hA008, 16'hA009, 16'hA00A, 16'hA00B, 16'hA00C : begin
      reg_write = 1'b1;
      mem_write = 1'b0;
      alu_op = 2'b10;
      alu_source = 1'b0; //reg2
      write_back_source = 2'b00; //alu_result
      branch = 1'b0;
      jump = 1'b0;
      itype_src2_rs1 = 1'b0;
      imm_source = 3'b000;
      second_add_source = 2'b00;
    end
    // B-type (BEQ, BLT,BNE, BGT)
    16'hD003, 16'hD004, 16'hD005, 16'hD00A, 16'hD00B, 16'hD00C: begin
      reg_write = 1'b0;
      imm_source = 3'b010;
      alu_op = 2'b01;
      alu_source = 1'b0;
      mem_write = 1'b0;
      branch = 1'b1;
      jump = 1'b0;
      write_back_source = 2'b00;
      itype_src2_rs1 = 1'b0;
      second_add_source = 2'b00;
    end
    // J-type (JUMP)
    16'hE010: begin
      reg_write = 1'b1;
      imm_source = 3'b011;
      alu_source = 1'b0;
      mem_write = 1'b0;
      write_back_source = 2'b10;
      branch = 1'b0;
      jump = 1'b1;
      itype_src2_rs1 = 1'b0;
      second_add_source = 2'b00;
    end
    // JALR (Jump and Link), this is a weird one. Encoded with "B" because it's encoded like
    // an I-type. "E" to designate a "subtype" of being a jump.
    16'hBE00: begin
      reg_write = 1'b1;
      imm_source = 3'b000;
      alu_source = 1'b0; // I think this is right???
      mem_write = 1'b0;
      write_back_source = 2'b10;
      branch = 1'b0;
      jump = 1'b1;
      second_add_source = 2'b10;
      itype_src2_rs1 = 1'b1;
    end
    // ALU I-type (addi, andi, ori, subi, slti, sltiu, xori, slli, srli, srai, nei, sgti, sgtiu)
    16'hB000, 16'hB001, 16'hB002, 16'hB003, 16'hB004, 16'hB005, 16'hB006, 16'hB007, 16'hB008, 16'hB009, 16'hB00A, 16'hB00B, 16'hB00C: begin
      reg_write = 1'b1;
      imm_source = 3'b000;
      alu_source = 1'b1; //imm
      mem_write = 1'b0;
      alu_op = 2'b10;
      write_back_source = 2'b00; //alu_result
      branch = 1'b0;
      jump = 1'b0;
      itype_src2_rs1 = 1'b1;
      second_add_source = 2'b00;
    end

    // U-type
    16'hF010, 16'hF011: begin
      imm_source = 3'b100;
      mem_write = 1'b0;
      reg_write = 1'b1;
      write_back_source = 2'b11;
      branch = 1'b0;
      jump = 1'b0;
      itype_src2_rs1 = 1'b1; // We need this for u-type as well
      case(op[0])
        1'b1: second_add_source = 2'b01; // lui
        1'b0: second_add_source = 2'b00; // auipc
      endcase
    end
    //EVERYTHING ELSE
    default: begin
        reg_write = 1'b0;
        imm_source = 3'b000;
        mem_write = 1'b0;
        alu_op = 2'b00;
        write_back_source = 2'b00;
        branch = 1'b0;
        jump = 1'b0;
        itype_src2_rs1 = 1'b0;
        second_add_source = 2'b00;
      end
    endcase
  end

  // ADDED TO DEAL WITH CHANGING DESTINATION TO R1 FOR BRANCH INSTRUCTIONS
assign branch_inst = branch;

/**
* ALU DECODER
*/

always_comb begin
    case (alu_op)
        // LW, SW
        2'b00: alu_control = 4'h0;
        // R-Types
        2'b10: begin
          //if anyone looks at this that isn't the original author
          //just know that this is inherited from a RISC-V CPU and I just liked to keep it like this
          //for the sake of labeling and keeping track.
          //Probably can just put everything below as alu_control = func4;
          case (func4)
            // ADD (SUB will NOT utilize F8, and for now there is no F8)
            4'h0: alu_control = 4'h0;
            // AND
            4'h1: alu_control = 4'h1;
            // OR
            4'h2: alu_control = 4'h2;
            // SUB
            4'h3: alu_control = 4'h3;
            //SLT (and SLTI)
            4'h4: alu_control = 4'h4;
            //SLTIU
            4'h5: alu_control = 4'h5;
            // XOR
            4'h6: alu_control = 4'h6;
            // SLL
            4'h7: alu_control = 4'h7;
            // SRL
            4'h8: alu_control = 4'h8;
            // SRA
            4'h9: alu_control = 4'h9;
            // NE
            4'hA: alu_control = 4'hA;
            // SGT (Set Greater Than)
            4'hB: alu_control = 4'hB;
            // SGTU (Set Greater Than unsigned)
            4'hC: alu_control = 4'hC;
            // ALL THE OTHERS
            default: alu_control = 4'hF;
          endcase
        end
        2'b01: begin
          case (func4)
            // BEQ
            4'h3: alu_control = 4'h3;
            // BLT
            4'h4: alu_control = 4'h4;
            // BLTU
            4'h5: alu_control = 4'h5;
            // BNE
            4'hA: alu_control = 4'hA;
            // BGT
            4'hB: alu_control = 4'hB;
            // BGTU
            4'hC: alu_control = 4'hC;
            default: alu_control = 4'h0;
          endcase
        end
        // EVERYTHING ELSE
        2'b11: alu_control = 4'hF;
       // default: alu_control = 4'b1111;
    endcase
end

logic assert_branch;

//Jumpscared into requesting func4? Nope! I'll just use the opcode!
always_comb begin: branch_logic_decode
  case (op)
    //BEQ
    16'hD003: assert_branch = alu_zero & branch;
    //BLT, BLTU, BNE, BGT
    16'hD004, 16'hD005, 16'hD00A, 16'hD00B, 16'hD00C: assert_branch = alu_last_bit & branch;
    default : assert_branch = 1'b0;
  endcase
end

/*
* pc_source
*/
assign pc_source = assert_branch | jump;

endmodule

control/dump.vcd
$version Generated by VerilatedVcd $end
$timescale 1ps $end
 $scope module $rootio $end
  $var wire 16 # op [15:0] $end
  $var wire 4 $ func4 [3:0] $end
  $var wire 8 % func8 [7:0] $end
  $var wire 1 & alu_zero $end
  $var wire 1 ' alu_last_bit $end
  $var wire 4 ( alu_control [3:0] $end
  $var wire 3 ) imm_source [2:0] $end
  $var wire 1 * mem_write $end
  $var wire 1 + reg_write $end
  $var wire 1 , alu_source $end
  $var wire 2 - write_back_source [1:0] $end
  $var wire 1 . pc_source $end
  $var wire 1 / branch_inst $end
  $var wire 1 0 itype_src2_rs1 $end
  $var wire 2 1 second_add_source [1:0] $end
 $upscope $end
 $scope module control $end
  $var wire 16 2 op [15:0] $end
  $var wire 4 3 func4 [3:0] $end
  $var wire 8 4 func8 [7:0] $end
  $var wire 1 5 alu_zero $end
  $var wire 1 6 alu_last_bit $end
  $var wire 4 7 alu_control [3:0] $end
  $var wire 3 8 imm_source [2:0] $end
  $var wire 1 9 mem_write $end
  $var wire 1 : reg_write $end
  $var wire 1 ; alu_source $end
  $var wire 2 < write_back_source [1:0] $end
  $var wire 1 = pc_source $end
  $var wire 1 > branch_inst $end
  $var wire 1 ? itype_src2_rs1 $end
  $var wire 2 @ second_add_source [1:0] $end
  $var wire 2 A alu_op [1:0] $end
  $var wire 1 B branch $end
  $var wire 1 C jump $end
  $var wire 1 D assert_branch $end
 $upscope $end
$enddefinitions $end


#0
b0000000000000000 #
b0000 $
b00000000 %
0&
0'
b0000 (
b000 )
0*
0+
0,
b00 -
0.
0/
00
b00 1
b0000000000000000 2
b0000 3
b00000000 4
05
06
b0000 7
b000 8
09
0:
0;
b00 <
0=
0>
0?
b00 @
b00 A
0B
0C
0D
#3000
b1011000000010000 #
1+
1,
b01 -
b1011000000010000 2
1:
1;
b01 <
#15001
b0000000000000000 #
0+
b00 -
b0000000000000000 2
0:
b00 <
#26001
b1100000000010000 #
b001 )
1*
b1100000000010000 2
b001 8
19
#28002
b0000000000000000 #
b000 )
0*
b0000000000000000 2
b000 8
09
#39002
b1010000000000000 #
1+
0,
b1010000000000000 2
1:
0;
b10 A
#41003
b0000000000000000 #
0+
b0000000000000000 2
0:
b00 A
#52003
b1010000000000001 #
b0001 $
b0001 (
1+
b1010000000000001 2
b0001 3
b0001 7
1:
b10 A
#54004
b0000000000000000 #
b0000 (
0+
b0000000000000000 2
b0000 7
0:
b00 A
#65004
b1010000000000010 #
b0010 $
b0010 (
1+
b1010000000000010 2
b0010 3
b0010 7
1:
b10 A
#67005
b0000000000000000 #
b0000 (
0+
b0000000000000000 2
b0000 7
0:
b00 A
#78005
b1101000000000011 #
b0011 $
b0011 (
b010 )
1/
b1101000000000011 2
b0011 3
b0011 7
b010 8
1>
b01 A
1B
#82005
1&
1.
15
1=
1D
#84006
b0000000000000000 #
b0000 (
b000 )
0.
0/
b0000000000000000 2
b0000 7
b000 8
0=
0>
b00 A
0B
0D
#95006
b1110000000010000 #
b011 )
1+
b10 -
1.
b1110000000010000 2
b011 8
1:
b10 <
1=
1C
#97007
b0000000000000000 #
b000 )
0+
b00 -
0.
b0000000000000000 2
b000 8
0:
b00 <
0=
0C
#108007
b1011000000000000 #
b0000 $
1+
1,
10
b1011000000000000 2
b0000 3
1:
1;
1?
b10 A
#110008
b0000000000000000 #
0+
00
b0000000000000000 2
0:
0?
b00 A
#121008
b1111000000010000 #
b100 )
1+
b11 -
10
b1111000000010000 2
b100 8
1:
b11 <
1?
#123009
b0000000000000000 #
b000 )
0+
b00 -
00
b0000000000000000 2
b000 8
0:
b00 <
0?
#134009
b1011000000000100 #
b0100 $
b0100 (
1+
10
b1011000000000100 2
b0100 3
b0100 7
1:
1?
b10 A
#136010
b0000000000000000 #
b0000 (
0+
00
b0000000000000000 2
b0000 7
0:
0?
b00 A
#147010
b1011000000000101 #
b0101 $
b0101 (
1+
10
b1011000000000101 2
b0101 3
b0101 7
1:
1?
b10 A
#149011
b0000000000000000 #
b0000 (
0+
00
b0000000000000000 2
b0000 7
0:
0?
b00 A
#160011
b1011000000000110 #
b0110 $
b0110 (
1+
10
b1011000000000110 2
b0110 3
b0110 7
1:
1?
b10 A
#162012
b0000000000000000 #
b0000 (
0+
00
b0000000000000000 2
b0000 7
0:
0?
b00 A
#173012
b1011000000000010 #
b0010 $
b0010 (
1+
10
b1011000000000010 2
b0010 3
b0010 7
1:
1?
b10 A
#175013
b0000000000000000 #
b0000 (
0+
00
b0000000000000000 2
b0000 7
0:
0?
b00 A
#186013
b1011000000000001 #
b0001 $
b0001 (
1+
10
b1011000000000001 2
b0001 3
b0001 7
1:
1?
b10 A
#188014
b0000000000000000 #
b0000 (
0+
00
b0000000000000000 2
b0000 7
0:
0?
b00 A
#199014
b1011000000000111 #
b0111 $
b0111 (
1+
10
b1011000000000111 2
b0111 3
b0111 7
1:
1?
b10 A
#201015
b0000000000000000 #
b0000 (
0+
00
b0000000000000000 2
b0000 7
0:
0?
b00 A
#212015
b1011000000001000 #
b1000 $
b1000 (
1+
10
b1011000000001000 2
b1000 3
b1000 7
1:
1?
b10 A
#214016
b0000000000000000 #
b0000 (
0+
00
b0000000000000000 2
b0000 7
0:
0?
b00 A
#225016
b1011000000001001 #
b1001 $
b1001 (
1+
10
b1011000000001001 2
b1001 3
b1001 7
1:
1?
b10 A
#227017
b0000000000000000 #
b0000 (
0+
00
b0000000000000000 2
b0000 7
0:
0?
b00 A
#238017
b1010000000000011 #
b0011 $
b0011 (
1+
0,
b1010000000000011 2
b0011 3
b0011 7
1:
0;
b10 A
#240018
b0000000000000000 #
b0000 (
0+
b0000000000000000 2
b0000 7
0:
b00 A
#251018
b1010000000000100 #
b0100 $
b0100 (
1+
b1010000000000100 2
b0100 3
b0100 7
1:
b10 A
#253019
b0000000000000000 #
b0000 (
0+
b0000000000000000 2
b0000 7
0:
b00 A
#264019
b1010000000000101 #
b0101 $
b0101 (
1+
b1010000000000101 2
b0101 3
b0101 7
1:
b10 A
#266020
b0000000000000000 #
b0000 (
0+
b0000000000000000 2
b0000 7
0:
b00 A
#277020
b1010000000000110 #
b0110 $
b0110 (
1+
b1010000000000110 2
b0110 3
b0110 7
1:
b10 A
#279021
b0000000000000000 #
b0000 (
0+
b0000000000000000 2
b0000 7
0:
b00 A
#290021
b1010000000000111 #
b0111 $
b0111 (
1+
b1010000000000111 2
b0111 3
b0111 7
1:
b10 A
#292022
b0000000000000000 #
b0000 (
0+
b0000000000000000 2
b0000 7
0:
b00 A
#303022
b1010000000001000 #
b1000 $
b1000 (
1+
b1010000000001000 2
b1000 3
b1000 7
1:
b10 A
#305023
b0000000000000000 #
b0000 (
0+
b0000000000000000 2
b0000 7
0:
b00 A
#316023
b1010000000001001 #
b1001 $
b1001 (
1+
b1010000000001001 2
b1001 3
b1001 7
1:
b10 A
#318024
b0000000000000000 #
b0000 (
0+
b0000000000000000 2
b0000 7
0:
b00 A
#329024
b1101000000000100 #
b0100 $
b0100 (
b010 )
1/
b1101000000000100 2
b0100 3
b0100 7
b010 8
1>
b01 A
1B
#333024
1'
1.
16
1=
1D
#335025
b0000000000000000 #
b0000 (
b000 )
0.
0/
b0000000000000000 2
b0000 7
b000 8
0=
0>
b00 A
0B
0D
#346025
b1101000000001010 #
b1010 $
0'
b1010 (
b010 )
1/
b1101000000001010 2
b1010 3
06
b1010 7
b010 8
1>
b01 A
1B
#350025
1'
1.
16
1=
1D
#352026
b0000000000000000 #
b0000 (
b000 )
0.
0/
b0000000000000000 2
b0000 7
b000 8
0=
0>
b00 A
0B
0D
#363026
b1101000000001011 #
b1011 $
0'
b1011 (
b010 )
1/
b1101000000001011 2
b1011 3
06
b1011 7
b010 8
1>
b01 A
1B
#367026
1'
1.
16
1=
1D
#369027
b0000000000000000 #
b0000 (
b000 )
0.
0/
b0000000000000000 2
b0000 7
b000 8
0=
0>
b00 A
0B
0D
#380027
b1101000000001011 #
0'
b1011 (
b010 )
1/
b1101000000001011 2
06
b1011 7
b010 8
1>
b01 A
1B
#384027
1'
1.
16
1=
1D
#386028
b0000000000000000 #
b0000 (
b000 )
0.
0/
b0000000000000000 2
b0000 7
b000 8
0=
0>
b00 A
0B
0D
#397028
b1101000000001100 #
b1100 $
0'
b1100 (
b010 )
1/
b1101000000001100 2
b1100 3
06
b1100 7
b010 8
1>
b01 A
1B
#401028
1'
1.
16
1=
1D
#403029
b0000000000000000 #
b0000 (
b000 )
0.
0/
b0000000000000000 2
b0000 7
b000 8
0=
0>
b00 A
0B
0D
#414029
b1011111000000000 #
1+
b10 -
1.
10
b10 1
b1011111000000000 2
1:
b10 <
1=
1?
b10 @
1C
