reader/reader.sv
// reader.sv

module reader(
    input logic [63:0] mem_data,
    input logic [7:0] byteMask,
    input logic [3:0] f4,

    output logic [63:0] writeBack,
    output logic valid);

logic sign_extend;
assign sign_extend = ~f4[3];

logic [63:0] masked_data; // just a mask applied
logic [63:0] raw_data;    // Data shifted according to instruction
                          // and then mem_data is the final output with sign extension

always_comb begin: mask_apply
    for (int i=0; i<8; i++) begin
        if (byteMask[i]) begin
            masked_data[(i*8)+:8] = mem_data [(i*8)+:8];
        end else begin
            masked_data[(i*8)+:8] = 8'h00;
        end
    end
end

always_comb begin : shift_data
    case (f4)
        4'b0100 : raw_data = masked_data; // masked data is the WORLD (full word) in that case

        4'b0000, 4'b1000: begin // LoadByte and LoadByteUnsigned
            case (byteMask)
                8'b00000001: raw_data = masked_data;
                8'b00000010: raw_data = masked_data >> 8;
                8'b00000100: raw_data = masked_data >> 16;
                8'b00001000: raw_data = masked_data >> 24;
                8'b00010000: raw_data = masked_data >> 32;
                8'b00100000: raw_data = masked_data >> 40;
                8'b01000000: raw_data = masked_data >> 48;
                8'b10000000: raw_data = masked_data >> 56;
                default: raw_data = 64'b0;
            endcase
        end

        4'b0001, 4'b1001: begin // (2bytes, quarter-words)
            case (byteMask)
                8'b00000011: raw_data = masked_data;
                8'b00001100: raw_data = masked_data >> 16;
                8'b00110000: raw_data = masked_data >> 32;
                8'b11000000: raw_data = masked_data >> 48;
                default: raw_data = 64'b0;
            endcase
        end

        4'b0010, 4'b1010: begin // (4bytes, half-words)
            case (byteMask)
                8'b00001111: raw_data = masked_data;
                8'b11110000: raw_data = masked_data >> 32;
                default: raw_data = 64'b0;
            endcase
        end

        default: raw_data = 64'b0;
    endcase
end

always_comb begin: sign_extend_logic
    case (f4)
    // Load 8byte
    4'b0100 : writeBack = raw_data;
    // Load byte
    4'b0000, 4'b1000: writeBack = sign_extend ? {{56{raw_data[7]}},raw_data[7:0]} : raw_data;
    // Load 2byte
    4'b0001, 4'b1001: writeBack = sign_extend ? {{48{raw_data[15]}},raw_data[15:0]} : raw_data;
    // Load 4byte
    4'b0010, 4'b1010: writeBack = sign_extend ? {{32{raw_data[31]}},raw_data[31:0]} : raw_data;

    default: writeBack = 64'b0; // Added missing default
    endcase

    valid = |byteMask;
end

endmodule

reader/dump.vcd
$version Generated by VerilatedVcd $end
$timescale 1ps $end
 $scope module $rootio $end
  $var wire 64 # mem_data [63:0] $end
  $var wire 8 % byteMask [7:0] $end
  $var wire 4 & f4 [3:0] $end
  $var wire 64 ' writeBack [63:0] $end
  $var wire 1 ) valid $end
 $upscope $end
 $scope module reader $end
  $var wire 64 * mem_data [63:0] $end
  $var wire 8 , byteMask [7:0] $end
  $var wire 4 - f4 [3:0] $end
  $var wire 64 . writeBack [63:0] $end
  $var wire 1 0 valid $end
  $var wire 1 1 sign_extend $end
  $var wire 64 2 masked_data [63:0] $end
  $var wire 64 4 raw_data [63:0] $end
  $scope module mask_apply $end
   $scope module unnamedblk1 $end
    $var wire 32 6 i [31:0] $end
   $upscope $end
  $upscope $end
 $upscope $end
$enddefinitions $end


#0
b0000000000000000000000000000000000000000000000000000000000000000 #
b00000000 %
b0100 &
b0000000000000000000000000000000000000000000000000000000000000000 '
0)
b0000000000000000000000000000000000000000000000000000000000000000 *
b00000000 ,
b0100 -
b0000000000000000000000000000000000000000000000000000000000000000 .
00
11
b0000000000000000000000000000000000000000000000000000000000000000 2
b0000000000000000000000000000000000000000000000000000000000000000 4
b00000000000000000000000000001000 6
#1000
b11111111 %
1)
b11111111 ,
10
#2000
b0010100110100011000101100110111001000101011010001001011010111000 #
b0010100110100011000101100110111001000101011010001001011010111000 '
b0010100110100011000101100110111001000101011010001001011010111000 *
b0010100110100011000101100110111001000101011010001001011010111000 .
b0010100110100011000101100110111001000101011010001001011010111000 2
b0010100110100011000101100110111001000101011010001001011010111000 4
#3000
b1011011101010010011101110100000000010110101101001101111110101111 #
b1011011101010010011101110100000000010110101101001101111110101111 '
b1011011101010010011101110100000000010110101101001101111110101111 *
b1011011101010010011101110100000000010110101101001101111110101111 .
b1011011101010010011101110100000000010110101101001101111110101111 2
b1011011101010010011101110100000000010110101101001101111110101111 4
#4000
b1111101100111110011110110010001011001111100110111011011110011110 #
b1111101100111110011110110010001011001111100110111011011110011110 '
b1111101100111110011110110010001011001111100110111011011110011110 *
b1111101100111110011110110010001011001111100110111011011110011110 .
b1111101100111110011110110010001011001111100110111011011110011110 2
b1111101100111110011110110010001011001111100110111011011110011110 4
#5000
b1100001001101001111001110011001001111010011100011111001101101000 #
b1100001001101001111001110011001001111010011100011111001101101000 '
b1100001001101001111001110011001001111010011100011111001101101000 *
b1100001001101001111001110011001001111010011100011111001101101000 .
b1100001001101001111001110011001001111010011100011111001101101000 2
b1100001001101001111001110011001001111010011100011111001101101000 4
#6000
b0110010011010001111100000001010110101001000000000100100111001100 #
b0110010011010001111100000001010110101001000000000100100111001100 '
b0110010011010001111100000001010110101001000000000100100111001100 *
b0110010011010001111100000001010110101001000000000100100111001100 .
b0110010011010001111100000001010110101001000000000100100111001100 2
b0110010011010001111100000001010110101001000000000100100111001100 4
#7000
b1011111001101101010000001011011000011111100111011110110000011111 #
b1011111001101101010000001011011000011111100111011110110000011111 '
b1011111001101101010000001011011000011111100111011110110000011111 *
b1011111001101101010000001011011000011111100111011110110000011111 .
b1011111001101101010000001011011000011111100111011110110000011111 2
b1011111001101101010000001011011000011111100111011110110000011111 4
#8000
b0101100111010000100100110001110011100000100101111010110101111010 #
b0101100111010000100100110001110011100000100101111010110101111010 '
b0101100111010000100100110001110011100000100101111010110101111010 *
b0101100111010000100100110001110011100000100101111010110101111010 .
b0101100111010000100100110001110011100000100101111010110101111010 2
b0101100111010000100100110001110011100000100101111010110101111010 4
#9000
b0001100100000000101011010110110111011101000000110111000001100001 #
b0001100100000000101011010110110111011101000000110111000001100001 '
b0001100100000000101011010110110111011101000000110111000001100001 *
b0001100100000000101011010110110111011101000000110111000001100001 .
b0001100100000000101011010110110111011101000000110111000001100001 2
b0001100100000000101011010110110111011101000000110111000001100001 4
#10000
b0001001001101111110000111000000001111110100101101001100011000001 #
b0001001001101111110000111000000001111110100101101001100011000001 '
b0001001001101111110000111000000001111110100101101001100011000001 *
b0001001001101111110000111000000001111110100101101001100011000001 .
b0001001001101111110000111000000001111110100101101001100011000001 2
b0001001001101111110000111000000001111110100101101001100011000001 4
#11000
b1001100000010101000001101011100100001000011100110101000000111001 #
b1001100000010101000001101011100100001000011100110101000000111001 '
b1001100000010101000001101011100100001000011100110101000000111001 *
b1001100000010101000001101011100100001000011100110101000000111001 .
b1001100000010101000001101011100100001000011100110101000000111001 2
b1001100000010101000001101011100100001000011100110101000000111001 4
#12000
b1011011101110100110001001111011010110011010000001101110011110100 #
b1011011101110100110001001111011010110011010000001101110011110100 '
b1011011101110100110001001111011010110011010000001101110011110100 *
b1011011101110100110001001111011010110011010000001101110011110100 .
b1011011101110100110001001111011010110011010000001101110011110100 2
b1011011101110100110001001111011010110011010000001101110011110100 4
#13000
b0000101100100101101101001000110011111000010000111101001010110110 #
b0000101100100101101101001000110011111000010000111101001010110110 '
b0000101100100101101101001000110011111000010000111101001010110110 *
b0000101100100101101101001000110011111000010000111101001010110110 .
b0000101100100101101101001000110011111000010000111101001010110110 2
b0000101100100101101101001000110011111000010000111101001010110110 4
#14000
b1111010111011010010110010010000001010000100001100010101001101111 #
b1111010111011010010110010010000001010000100001100010101001101111 '
b1111010111011010010110010010000001010000100001100010101001101111 *
b1111010111011010010110010010000001010000100001100010101001101111 .
b1111010111011010010110010010000001010000100001100010101001101111 2
b1111010111011010010110010010000001010000100001100010101001101111 4
#15000
b0000011110001011101100001100010000110010011011000100111101101010 #
b0000011110001011101100001100010000110010011011000100111101101010 '
b0000011110001011101100001100010000110010011011000100111101101010 *
b0000011110001011101100001100010000110010011011000100111101101010 .
b0000011110001011101100001100010000110010011011000100111101101010 2
b0000011110001011101100001100010000110010011011000100111101101010 4
#16000
b0100010010101011010010110100000000001101111100100001110101111101 #
b0100010010101011010010110100000000001101111100100001110101111101 '
b0100010010101011010010110100000000001101111100100001110101111101 *
b0100010010101011010010110100000000001101111100100001110101111101 .
b0100010010101011010010110100000000001101111100100001110101111101 2
b0100010010101011010010110100000000001101111100100001110101111101 4
#17000
b0011011101111100011101001100000111110111000101100101111101111110 #
b0011011101111100011101001100000111110111000101100101111101111110 '
b0011011101111100011101001100000111110111000101100101111101111110 *
b0011011101111100011101001100000111110111000101100101111101111110 .
b0011011101111100011101001100000111110111000101100101111101111110 2
b0011011101111100011101001100000111110111000101100101111101111110 4
#18000
b0001111111001100111110101110100100011001111000110101101100100101 #
b0001111111001100111110101110100100011001111000110101101100100101 '
b0001111111001100111110101110100100011001111000110101101100100101 *
b0001111111001100111110101110100100011001111000110101101100100101 .
b0001111111001100111110101110100100011001111000110101101100100101 2
b0001111111001100111110101110100100011001111000110101101100100101 4
#19000
b0101010111010110110111111011101100100111110011010010001001101110 #
b0101010111010110110111111011101100100111110011010010001001101110 '
b0101010111010110110111111011101100100111110011010010001001101110 *
b0101010111010110110111111011101100100111110011010010001001101110 .
b0101010111010110110111111011101100100111110011010010001001101110 2
b0101010111010110110111111011101100100111110011010010001001101110 4
#20000
b0011110101100001110100011000001110001001001001001000001010001100 #
b0011110101100001110100011000001110001001001001001000001010001100 '
b0011110101100001110100011000001110001001001001001000001010001100 *
b0011110101100001110100011000001110001001001001001000001010001100 .
b0011110101100001110100011000001110001001001001001000001010001100 2
b0011110101100001110100011000001110001001001001001000001010001100 4
#21000
b0101010110000001101011100000111111001011111111111110100110111100 #
b0101010110000001101011100000111111001011111111111110100110111100 '
b0101010110000001101011100000111111001011111111111110100110111100 *
b0101010110000001101011100000111111001011111111111110100110111100 .
b0101010110000001101011100000111111001011111111111110100110111100 2
b0101010110000001101011100000111111001011111111111110100110111100 4
#22000
b0110111111100100101000101000011111111100011101111101010101010010 #
b0110111111100100101000101000011111111100011101111101010101010010 '
b0110111111100100101000101000011111111100011101111101010101010010 *
b0110111111100100101000101000011111111100011101111101010101010010 .
b0110111111100100101000101000011111111100011101111101010101010010 2
b0110111111100100101000101000011111111100011101111101010101010010 4
#23000
b1001001010101001011010110000010110010101101001111001001101100010 #
b1001001010101001011010110000010110010101101001111001001101100010 '
b1001001010101001011010110000010110010101101001111001001101100010 *
b1001001010101001011010110000010110010101101001111001001101100010 .
b1001001010101001011010110000010110010101101001111001001101100010 2
b1001001010101001011010110000010110010101101001111001001101100010 4
#24000
b0100001111000011100111111101100100100110011101100001010110101101 #
b0100001111000011100111111101100100100110011101100001010110101101 '
b0100001111000011100111111101100100100110011101100001010110101101 *
b0100001111000011100111111101100100100110011101100001010110101101 .
b0100001111000011100111111101100100100110011101100001010110101101 2
b0100001111000011100111111101100100100110011101100001010110101101 4
#25000
b1011111001011011111011111010101010011010100101000110010001111010 #
b1011111001011011111011111010101010011010100101000110010001111010 '
b1011111001011011111011111010101010011010100101000110010001111010 *
b1011111001011011111011111010101010011010100101000110010001111010 .
b1011111001011011111011111010101010011010100101000110010001111010 2
b1011111001011011111011111010101010011010100101000110010001111010 4
#26000
b0001001110111111011110001000010011101101011010000100101010011101 #
b0001001110111111011110001000010011101101011010000100101010011101 '
b0001001110111111011110001000010011101101011010000100101010011101 *
b0001001110111111011110001000010011101101011010000100101010011101 .
b0001001110111111011110001000010011101101011010000100101010011101 2
b0001001110111111011110001000010011101101011010000100101010011101 4
#27000
b0010010001010011011110111111100001000100011001101110111101001100 #
b0010010001010011011110111111100001000100011001101110111101001100 '
b0010010001010011011110111111100001000100011001101110111101001100 *
b0010010001010011011110111111100001000100011001101110111101001100 .
b0010010001010011011110111111100001000100011001101110111101001100 2
b0010010001010011011110111111100001000100011001101110111101001100 4
#28000
b1001001100001001000001000001100111110100100111000001111100001011 #
b1001001100001001000001000001100111110100100111000001111100001011 '
b1001001100001001000001000001100111110100100111000001111100001011 *
b1001001100001001000001000001100111110100100111000001111100001011 .
b1001001100001001000001000001100111110100100111000001111100001011 2
b1001001100001001000001000001100111110100100111000001111100001011 4
#29000
b0011001100111001010011101010110001110100000101011100011101111111 #
b0011001100111001010011101010110001110100000101011100011101111111 '
b0011001100111001010011101010110001110100000101011100011101111111 *
b0011001100111001010011101010110001110100000101011100011101111111 .
b0011001100111001010011101010110001110100000101011100011101111111 2
b0011001100111001010011101010110001110100000101011100011101111111 4
#30000
b0010011010001100100110001100110110010011001101101001100111000000 #
b0010011010001100100110001100110110010011001101101001100111000000 '
b0010011010001100100110001100110110010011001101101001100111000000 *
b0010011010001100100110001100110110010011001101101001100111000000 .
b0010011010001100100110001100110110010011001101101001100111000000 2
b0010011010001100100110001100110110010011001101101001100111000000 4
#31000
b0101010000011001101000010011111010001111000000011111101111010100 #
b0101010000011001101000010011111010001111000000011111101111010100 '
b0101010000011001101000010011111010001111000000011111101111010100 *
b0101010000011001101000010011111010001111000000011111101111010100 .
b0101010000011001101000010011111010001111000000011111101111010100 2
b0101010000011001101000010011111010001111000000011111101111010100 4
#32000
b1101110101011000101101101001100100001000000100010111110011001110 #
b1101110101011000101101101001100100001000000100010111110011001110 '
b1101110101011000101101101001100100001000000100010111110011001110 *
b1101110101011000101101101001100100001000000100010111110011001110 .
b1101110101011000101101101001100100001000000100010111110011001110 2
b1101110101011000101101101001100100001000000100010111110011001110 4
#33000
b0101101111011101000001100101001100011001111101010100100000001000 #
b0101101111011101000001100101001100011001111101010100100000001000 '
b0101101111011101000001100101001100011001111101010100100000001000 *
b0101101111011101000001100101001100011001111101010100100000001000 .
b0101101111011101000001100101001100011001111101010100100000001000 2
b0101101111011101000001100101001100011001111101010100100000001000 4
#34000
b1010111111011111010101111010010000000011100000010101011101000010 #
b1010111111011111010101111010010000000011100000010101011101000010 '
b1010111111011111010101111010010000000011100000010101011101000010 *
b1010111111011111010101111010010000000011100000010101011101000010 .
b1010111111011111010101111010010000000011100000010101011101000010 2
b1010111111011111010101111010010000000011100000010101011101000010 4
#35000
b1110101111100101011000000010101010001111100010010010000101100010 #
b1110101111100101011000000010101010001111100010010010000101100010 '
b1110101111100101011000000010101010001111100010010010000101100010 *
b1110101111100101011000000010101010001111100010010010000101100010 .
b1110101111100101011000000010101010001111100010010010000101100010 2
b1110101111100101011000000010101010001111100010010010000101100010 4
#36000
b0111101111110110111011011000101011111011001010000011110100011001 #
b0111101111110110111011011000101011111011001010000011110100011001 '
b0111101111110110111011011000101011111011001010000011110100011001 *
b0111101111110110111011011000101011111011001010000011110100011001 .
b0111101111110110111011011000101011111011001010000011110100011001 2
b0111101111110110111011011000101011111011001010000011110100011001 4
#37000
b1101110111111001011010010100011110111100101100111010100111111001 #
b1101110111111001011010010100011110111100101100111010100111111001 '
b1101110111111001011010010100011110111100101100111010100111111001 *
b1101110111111001011010010100011110111100101100111010100111111001 .
b1101110111111001011010010100011110111100101100111010100111111001 2
b1101110111111001011010010100011110111100101100111010100111111001 4
#38000
b0000110100000011111100000101000011000110100011011010011011011001 #
b0000110100000011111100000101000011000110100011011010011011011001 '
b0000110100000011111100000101000011000110100011011010011011011001 *
b0000110100000011111100000101000011000110100011011010011011011001 .
b0000110100000011111100000101000011000110100011011010011011011001 2
b0000110100000011111100000101000011000110100011011010011011011001 4
#39000
b0101001100001101000001001001110000011001110001100000000001101010 #
b0101001100001101000001001001110000011001110001100000000001101010 '
b0101001100001101000001001001110000011001110001100000000001101010 *
b0101001100001101000001001001110000011001110001100000000001101010 .
b0101001100001101000001001001110000011001110001100000000001101010 2
b0101001100001101000001001001110000011001110001100000000001101010 4
#40000
b1110111111101011001100111000011001001010000011100000110111000101 #
b1110111111101011001100111000011001001010000011100000110111000101 '
b1110111111101011001100111000011001001010000011100000110111000101 *
b1110111111101011001100111000011001001010000011100000110111000101 .
b1110111111101011001100111000011001001010000011100000110111000101 2
b1110111111101011001100111000011001001010000011100000110111000101 4
#41000
b1001011110110000110101001011100100110000000110111111111110000100 #
b1001011110110000110101001011100100110000000110111111111110000100 '
b1001011110110000110101001011100100110000000110111111111110000100 *
b1001011110110000110101001011100100110000000110111111111110000100 .
b1001011110110000110101001011100100110000000110111111111110000100 2
b1001011110110000110101001011100100110000000110111111111110000100 4
#42000
b1001101100111101111001100111111001100011110001011111011010000110 #
b1001101100111101111001100111111001100011110001011111011010000110 '
b1001101100111101111001100111111001100011110001011111011010000110 *
b1001101100111101111001100111111001100011110001011111011010000110 .
b1001101100111101111001100111111001100011110001011111011010000110 2
b1001101100111101111001100111111001100011110001011111011010000110 4
#43000
b1111111101101000010010100011001101110001011000010101111111110110 #
b1111111101101000010010100011001101110001011000010101111111110110 '
b1111111101101000010010100011001101110001011000010101111111110110 *
b1111111101101000010010100011001101110001011000010101111111110110 .
b1111111101101000010010100011001101110001011000010101111111110110 2
b1111111101101000010010100011001101110001011000010101111111110110 4
#44000
b0110101111011001110101011010110100111000010111001001000010111111 #
b0110101111011001110101011010110100111000010111001001000010111111 '
b0110101111011001110101011010110100111000010111001001000010111111 *
b0110101111011001110101011010110100111000010111001001000010111111 .
b0110101111011001110101011010110100111000010111001001000010111111 2
b0110101111011001110101011010110100111000010111001001000010111111 4
#45000
b1011101001001001011010001000100111000001000011111001011111111010 #
b1011101001001001011010001000100111000001000011111001011111111010 '
b1011101001001001011010001000100111000001000011111001011111111010 *
b1011101001001001011010001000100111000001000011111001011111111010 .
b1011101001001001011010001000100111000001000011111001011111111010 2
b1011101001001001011010001000100111000001000011111001011111111010 4
#46000
b1001011100011010001101101100010000100011110100010011111101110000 #
b1001011100011010001101101100010000100011110100010011111101110000 '
b1001011100011010001101101100010000100011110100010011111101110000 *
b1001011100011010001101101100010000100011110100010011111101110000 .
b1001011100011010001101101100010000100011110100010011111101110000 2
b1001011100011010001101101100010000100011110100010011111101110000 4
#47000
b0101011111000111101111001001010111010110000101011011001001011110 #
b0101011111000111101111001001010111010110000101011011001001011110 '
b0101011111000111101111001001010111010110000101011011001001011110 *
b0101011111000111101111001001010111010110000101011011001001011110 .
b0101011111000111101111001001010111010110000101011011001001011110 2
b0101011111000111101111001001010111010110000101011011001001011110 4
#48000
b1011000011111011100110001010000011101110001100101010001000000101 #
b1011000011111011100110001010000011101110001100101010001000000101 '
b1011000011111011100110001010000011101110001100101010001000000101 *
b1011000011111011100110001010000011101110001100101010001000000101 .
b1011000011111011100110001010000011101110001100101010001000000101 2
b1011000011111011100110001010000011101110001100101010001000000101 4
#49000
b0100010001101011101110101110001000001110000111100001111010011010 #
b0100010001101011101110101110001000001110000111100001111010011010 '
b0100010001101011101110101110001000001110000111100001111010011010 *
b0100010001101011101110101110001000001110000111100001111010011010 .
b0100010001101011101110101110001000001110000111100001111010011010 2
b0100010001101011101110101110001000001110000111100001111010011010 4
#50000
b0001000000100111010001010000001110010011100110111000000110010000 #
b0001000000100111010001010000001110010011100110111000000110010000 '
b0001000000100111010001010000001110010011100110111000000110010000 *
b0001000000100111010001010000001110010011100110111000000110010000 .
b0001000000100111010001010000001110010011100110111000000110010000 2
b0001000000100111010001010000001110010011100110111000000110010000 4
#51000
b1110111100000111000000110101100000001110001111100011101010011011 #
b1110111100000111000000110101100000001110001111100011101010011011 '
b1110111100000111000000110101100000001110001111100011101010011011 *
b1110111100000111000000110101100000001110001111100011101010011011 .
b1110111100000111000000110101100000001110001111100011101010011011 2
b1110111100000111000000110101100000001110001111100011101010011011 4
#52000
b1111001010111110110111101000100111010010100111011100110001001001 #
b1111001010111110110111101000100111010010100111011100110001001001 '
b1111001010111110110111101000100111010010100111011100110001001001 *
b1111001010111110110111101000100111010010100111011100110001001001 .
b1111001010111110110111101000100111010010100111011100110001001001 2
b1111001010111110110111101000100111010010100111011100110001001001 4
#53000
b1011110110011110011110111100101001110001011111101101001111111010 #
b1011110110011110011110111100101001110001011111101101001111111010 '
b1011110110011110011110111100101001110001011111101101001111111010 *
b1011110110011110011110111100101001110001011111101101001111111010 .
b1011110110011110011110111100101001110001011111101101001111111010 2
b1011110110011110011110111100101001110001011111101101001111111010 4
#54000
b1001110011101001100111111101111111011010011110100011110110011001 #
b1001110011101001100111111101111111011010011110100011110110011001 '
b1001110011101001100111111101111111011010011110100011110110011001 *
b1001110011101001100111111101111111011010011110100011110110011001 .
b1001110011101001100111111101111111011010011110100011110110011001 2
b1001110011101001100111111101111111011010011110100011110110011001 4
#55000
b0000010111110101000101011101100010100100001001000111100010100000 #
b0000010111110101000101011101100010100100001001000111100010100000 '
b0000010111110101000101011101100010100100001001000111100010100000 *
b0000010111110101000101011101100010100100001001000111100010100000 .
b0000010111110101000101011101100010100100001001000111100010100000 2
b0000010111110101000101011101100010100100001001000111100010100000 4
#56000
b0000010110000111010101111111010010001001000011000010010010110111 #
b0000010110000111010101111111010010001001000011000010010010110111 '
b0000010110000111010101111111010010001001000011000010010010110111 *
b0000010110000111010101111111010010001001000011000010010010110111 .
b0000010110000111010101111111010010001001000011000010010010110111 2
b0000010110000111010101111111010010001001000011000010010010110111 4
#57000
b0010010110010010000010010110110101011100011101011101111100111110 #
b0010010110010010000010010110110101011100011101011101111100111110 '
b0010010110010010000010010110110101011100011101011101111100111110 *
b0010010110010010000010010110110101011100011101011101111100111110 .
b0010010110010010000010010110110101011100011101011101111100111110 2
b0010010110010010000010010110110101011100011101011101111100111110 4
#58000
b1011010111000011000100011010101001101111000110101100010100000010 #
b1011010111000011000100011010101001101111000110101100010100000010 '
b1011010111000011000100011010101001101111000110101100010100000010 *
b1011010111000011000100011010101001101111000110101100010100000010 .
b1011010111000011000100011010101001101111000110101100010100000010 2
b1011010111000011000100011010101001101111000110101100010100000010 4
#59000
b0111000001000101101101000010110111010010000000010101100010000110 #
b0111000001000101101101000010110111010010000000010101100010000110 '
b0111000001000101101101000010110111010010000000010101100010000110 *
b0111000001000101101101000010110111010010000000010101100010000110 .
b0111000001000101101101000010110111010010000000010101100010000110 2
b0111000001000101101101000010110111010010000000010101100010000110 4
#60000
b0101010110110010010010010000101100010010000100101011100111100010 #
b0101010110110010010010010000101100010010000100101011100111100010 '
b0101010110110010010010010000101100010010000100101011100111100010 *
b0101010110110010010010010000101100010010000100101011100111100010 .
b0101010110110010010010010000101100010010000100101011100111100010 2
b0101010110110010010010010000101100010010000100101011100111100010 4
#61000
b1000111111111001100111111001101100001010011010111111110001000111 #
b1000111111111001100111111001101100001010011010111111110001000111 '
b1000111111111001100111111001101100001010011010111111110001000111 *
b1000111111111001100111111001101100001010011010111111110001000111 .
b1000111111111001100111111001101100001010011010111111110001000111 2
b1000111111111001100111111001101100001010011010111111110001000111 4
#62000
b0110111100011110110000001011001101101001111011000101111011110111 #
b0110111100011110110000001011001101101001111011000101111011110111 '
b0110111100011110110000001011001101101001111011000101111011110111 *
b0110111100011110110000001011001101101001111011000101111011110111 .
b0110111100011110110000001011001101101001111011000101111011110111 2
b0110111100011110110000001011001101101001111011000101111011110111 4
#63000
b0011101010111101100111000111110100001100000000000110110110001011 #
b0011101010111101100111000111110100001100000000000110110110001011 '
b0011101010111101100111000111110100001100000000000110110110001011 *
b0011101010111101100111000111110100001100000000000110110110001011 .
b0011101010111101100111000111110100001100000000000110110110001011 2
b0011101010111101100111000111110100001100000000000110110110001011 4
#64000
b1010001001100001011000000110001011110010011100100001101001011100 #
b1010001001100001011000000110001011110010011100100001101001011100 '
b1010001001100001011000000110001011110010011100100001101001011100 *
b1010001001100001011000000110001011110010011100100001101001011100 .
b1010001001100001011000000110001011110010011100100001101001011100 2
b1010001001100001011000000110001011110010011100100001101001011100 4
#65000
b0001010111001100100101001010011010011000110110000111001010000001 #
b0001010111001100100101001010011010011000110110000111001010000001 '
b0001010111001100100101001010011010011000110110000111001010000001 *
b0001010111001100100101001010011010011000110110000111001010000001 .
b0001010111001100100101001010011010011000110110000111001010000001 2
b0001010111001100100101001010011010011000110110000111001010000001 4
#66000
b0100010110000111011010011100001010100101001110100010100000100101 #
b0100010110000111011010011100001010100101001110100010100000100101 '
b0100010110000111011010011100001010100101001110100010100000100101 *
b0100010110000111011010011100001010100101001110100010100000100101 .
b0100010110000111011010011100001010100101001110100010100000100101 2
b0100010110000111011010011100001010100101001110100010100000100101 4
#67000
b0011110111010110011100111010111110000011111110001010000011001000 #
b0011110111010110011100111010111110000011111110001010000011001000 '
b0011110111010110011100111010111110000011111110001010000011001000 *
b0011110111010110011100111010111110000011111110001010000011001000 .
b0011110111010110011100111010111110000011111110001010000011001000 2
b0011110111010110011100111010111110000011111110001010000011001000 4
#68000
b1010111010001000111001011011001100010101001101100111111011110101 #
b1010111010001000111001011011001100010101001101100111111011110101 '
b1010111010001000111001011011001100010101001101100111111011110101 *
b1010111010001000111001011011001100010101001101100111111011110101 .
b1010111010001000111001011011001100010101001101100111111011110101 2
b1010111010001000111001011011001100010101001101100111111011110101 4
#69000
b1111110001000001100011010010001100110001101110100000100000100111 #
b1111110001000001100011010010001100110001101110100000100000100111 '
b1111110001000001100011010010001100110001101110100000100000100111 *
b1111110001000001100011010010001100110001101110100000100000100111 .
b1111110001000001100011010010001100110001101110100000100000100111 2
b1111110001000001100011010010001100110001101110100000100000100111 4
#70000
b1111110011111011111110100110010111101011101011110110000100010111 #
b1111110011111011111110100110010111101011101011110110000100010111 '
b1111110011111011111110100110010111101011101011110110000100010111 *
b1111110011111011111110100110010111101011101011110110000100010111 .
b1111110011111011111110100110010111101011101011110110000100010111 2
b1111110011111011111110100110010111101011101011110110000100010111 4
#71000
b0001011000110000011010000111111000001010111000100100011000000100 #
b0001011000110000011010000111111000001010111000100100011000000100 '
b0001011000110000011010000111111000001010111000100100011000000100 *
b0001011000110000011010000111111000001010111000100100011000000100 .
b0001011000110000011010000111111000001010111000100100011000000100 2
b0001011000110000011010000111111000001010111000100100011000000100 4
#72000
b0011100000100000110011001111100000111001001111010011101111101000 #
b0011100000100000110011001111100000111001001111010011101111101000 '
b0011100000100000110011001111100000111001001111010011101111101000 *
b0011100000100000110011001111100000111001001111010011101111101000 .
b0011100000100000110011001111100000111001001111010011101111101000 2
b0011100000100000110011001111100000111001001111010011101111101000 4
#73000
b0100110101100010100000110000010111111000111101011010111001001011 #
b0100110101100010100000110000010111111000111101011010111001001011 '
b0100110101100010100000110000010111111000111101011010111001001011 *
b0100110101100010100000110000010111111000111101011010111001001011 .
b0100110101100010100000110000010111111000111101011010111001001011 2
b0100110101100010100000110000010111111000111101011010111001001011 4
#74000
b1101001000111011101001100010111111011110010001000011101011110111 #
b1101001000111011101001100010111111011110010001000011101011110111 '
b1101001000111011101001100010111111011110010001000011101011110111 *
b1101001000111011101001100010111111011110010001000011101011110111 .
b1101001000111011101001100010111111011110010001000011101011110111 2
b1101001000111011101001100010111111011110010001000011101011110111 4
#75000
b0001110110000011100110000100100001011100011101111111001000110110 #
b0001110110000011100110000100100001011100011101111111001000110110 '
b0001110110000011100110000100100001011100011101111111001000110110 *
b0001110110000011100110000100100001011100011101111111001000110110 .
b0001110110000011100110000100100001011100011101111111001000110110 2
b0001110110000011100110000100100001011100011101111111001000110110 4
#76000
b1101011000001100010101010000100010011101011001011000100000000010 #
b1101011000001100010101010000100010011101011001011000100000000010 '
b1101011000001100010101010000100010011101011001011000100000000010 *
b1101011000001100010101010000100010011101011001011000100000000010 .
b1101011000001100010101010000100010011101011001011000100000000010 2
b1101011000001100010101010000100010011101011001011000100000000010 4
#77000
b0011011100000111000001010010110100011010100001011011100010100010 #
b0011011100000111000001010010110100011010100001011011100010100010 '
b0011011100000111000001010010110100011010100001011011100010100010 *
b0011011100000111000001010010110100011010100001011011100010100010 .
b0011011100000111000001010010110100011010100001011011100010100010 2
b0011011100000111000001010010110100011010100001011011100010100010 4
#78000
b0001010111101101011001111001011101100100011010101101011000000001 #
b0001010111101101011001111001011101100100011010101101011000000001 '
b0001010111101101011001111001011101100100011010101101011000000001 *
b0001010111101101011001111001011101100100011010101101011000000001 .
b0001010111101101011001111001011101100100011010101101011000000001 2
b0001010111101101011001111001011101100100011010101101011000000001 4
#79000
b1000110111100011101100000100100100110011010000000001110001101001 #
b1000110111100011101100000100100100110011010000000001110001101001 '
b1000110111100011101100000100100100110011010000000001110001101001 *
b1000110111100011101100000100100100110011010000000001110001101001 .
b1000110111100011101100000100100100110011010000000001110001101001 2
b1000110111100011101100000100100100110011010000000001110001101001 4
#80000
b1001101010100011101000010001111110010111110101011001010010000010 #
b1001101010100011101000010001111110010111110101011001010010000010 '
b1001101010100011101000010001111110010111110101011001010010000010 *
b1001101010100011101000010001111110010111110101011001010010000010 .
b1001101010100011101000010001111110010111110101011001010010000010 2
b1001101010100011101000010001111110010111110101011001010010000010 4
#81000
b1100000101101100000010101010001111001011011111011011001111110001 #
b1100000101101100000010101010001111001011011111011011001111110001 '
b1100000101101100000010101010001111001011011111011011001111110001 *
b1100000101101100000010101010001111001011011111011011001111110001 .
b1100000101101100000010101010001111001011011111011011001111110001 2
b1100000101101100000010101010001111001011011111011011001111110001 4
#82000
b1100000100111101000100001100010000010000100110111111011011100010 #
b1100000100111101000100001100010000010000100110111111011011100010 '
b1100000100111101000100001100010000010000100110111111011011100010 *
b1100000100111101000100001100010000010000100110111111011011100010 .
b1100000100111101000100001100010000010000100110111111011011100010 2
b1100000100111101000100001100010000010000100110111111011011100010 4
#83000
b0111011101101100010100010111010000111001001010111100110111001001 #
b0111011101101100010100010111010000111001001010111100110111001001 '
b0111011101101100010100010111010000111001001010111100110111001001 *
b0111011101101100010100010111010000111001001010111100110111001001 .
b0111011101101100010100010111010000111001001010111100110111001001 2
b0111011101101100010100010111010000111001001010111100110111001001 4
