load_store.sv
// load_store.sv
module load_store (
    input logic [63:0] alu_result_address,
    input logic [3:0] f4,
    input logic [63:0] reg_read,
    output logic [7:0] byte_enable,
    output logic [63:0] data
);

logic [2:0] offset;

assign offset = alu_result_address[2:0];

always_comb begin
    case (f4)
        4'b0000, 4'b1000: begin // StoreByte or StoreSquad or Steigth (Store+Eighth)
            case (offset)
                3'b000: begin
                    byte_enable = 8'b00000001;
                    data = (reg_read & 64'h00000000000000FF);
                end
                3'b001: begin
                    byte_enable = 8'b00000010;
                    data = (reg_read & 64'h00000000000000FF) << 8;
                end
                3'b010: begin
                    byte_enable = 8'b00000100;
                    data = (reg_read & 64'h00000000000000FF) << 16;
                end
                3'b011: begin
                    byte_enable = 8'b00001000;
                    data = (reg_read & 64'h00000000000000FF) << 24;
                end
                3'b100: begin
                    byte_enable = 8'b00010000;
                    data = (reg_read & 64'h00000000000000FF) << 32;
                end
                3'b101: begin
                    byte_enable = 8'b00100000;
                    data = (reg_read & 64'h00000000000000FF) << 40;
                end
                3'b110: begin
                    byte_enable = 8'b01000000;
                    data = (reg_read & 64'h00000000000000FF) << 48;
                end
                3'b111: begin
                    byte_enable = 8'b10000000;
                    data = (reg_read & 64'h00000000000000FF) << 56;
                end
                default: byte_enable = 8'b00000000;
            endcase
        end
        4'b0001, 4'b1001: begin // StoreQuart or Squart (Store+quart) or StoreBrigade or Store2pac (2 byte... 2pac idk)
            case (offset)
                3'b000: begin
                    byte_enable = 8'b00000011;
                    data = (reg_read & 64'h000000000000FFFF);
                end
                3'b010: begin
                    byte_enable = 8'b00001100;
                    data = (reg_read & 64'h000000000000FFFF) << 16;
                end
                3'b100: begin
                    byte_enable = 8'b00110000;
                    data = (reg_read & 64'h000000000000FFFF) << 32;
                end
                3'b110: begin
                    byte_enable = 8'b11000000;
                    data = (reg_read & 64'h000000000000FFFF) << 48;
                end
                default: byte_enable = 8'b00000000;
            endcase
        end
        4'b0010, 4'b1010: begin // StoreChud or StoreChina or Stalf (Store+half)
            case (offset)
                3'b000: begin
                    byte_enable = 8'b00001111;
                    data = (reg_read & 64'h00000000FFFFFFFF);
                end
                3'b100: begin
                    byte_enable = 8'b11110000;
                    data = (reg_read & 64'h00000000FFFFFFFF) << 32;
                end
                default: byte_enable = 8'b00000000;
           endcase
        end
        4'b0100: begin // StoreWorld (yeah THE WORLD) or StoreFull
            byte_enable = (offset == 3'b000) ? 8'b11111111 : 8'b00000000;
            data = reg_read;
        end

        default: begin
            byte_enable = 8'b00000000; // No operation for unsupported types
        end
    endcase
end

endmodule

load_store/dump.vcd
$version Generated by VerilatedVcd $end
$timescale 1ps $end
 $scope module $rootio $end
  $var wire 64 # alu_result_address [63:0] $end
  $var wire 4 % f4 [3:0] $end
  $var wire 64 & reg_read [63:0] $end
  $var wire 8 ( byte_enable [7:0] $end
  $var wire 64 ) data [63:0] $end
 $upscope $end
 $scope module load_store $end
  $var wire 64 + alu_result_address [63:0] $end
  $var wire 4 - f4 [3:0] $end
  $var wire 64 . reg_read [63:0] $end
  $var wire 8 0 byte_enable [7:0] $end
  $var wire 64 1 data [63:0] $end
  $var wire 3 3 offset [2:0] $end
 $upscope $end
$enddefinitions $end


#0
b0111001001101111011000100110111101110100011011100110100100000000 #
b0100 %
b1110000110000110011110001010100010000001001110110100111000010110 &
b11111111 (
b1110000110000110011110001010100010000001001110110100111000010110 )
b0111001001101111011000100110111101110100011011100110100100000000 +
b0100 -
b1110000110000110011110001010100010000001001110110100111000010110 .
b11111111 0
b1110000110000110011110001010100010000001001110110100111000010110 1
b000 3
#1000
b0111001001101111011000100110111101110100011011100110100100000001 #
b00000000 (
b0111001001101111011000100110111101110100011011100110100100000001 +
b00000000 0
b001 3
#2000
b0111001001101111011000100110111101110100011011100110100100000010 #
b0111001001101111011000100110111101110100011011100110100100000010 +
b010 3
#3000
b0111001001101111011000100110111101110100011011100110100100000011 #
b0111001001101111011000100110111101110100011011100110100100000011 +
b011 3
#4000
b0111001001101111011000100110111101110100011011100110100100000100 #
b0111001001101111011000100110111101110100011011100110100100000100 +
b100 3
#5000
b0111001001101111011000100110111101110100011011100110100100000101 #
b0111001001101111011000100110111101110100011011100110100100000101 +
b101 3
#6000
b0111001001101111011000100110111101110100011011100110100100000110 #
b0111001001101111011000100110111101110100011011100110100100000110 +
b110 3
#7000
b0111001001101111011000100110111101110100011011100110100100000111 #
b0111001001101111011000100110111101110100011011100110100100000111 +
b111 3
#8000
b0111001001101111011000100110111101110100011011100110100100000000 #
b1111011001110010101000001100111010100101101001101000101110010110 &
b11111111 (
b1111011001110010101000001100111010100101101001101000101110010110 )
b0111001001101111011000100110111101110100011011100110100100000000 +
b1111011001110010101000001100111010100101101001101000101110010110 .
b11111111 0
b1111011001110010101000001100111010100101101001101000101110010110 1
b000 3
#9000
b0111001001101111011000100110111101110100011011100110100100000001 #
b00000000 (
b0111001001101111011000100110111101110100011011100110100100000001 +
b00000000 0
b001 3
#10000
b0111001001101111011000100110111101110100011011100110100100000010 #
b0111001001101111011000100110111101110100011011100110100100000010 +
b010 3
#11000
b0111001001101111011000100110111101110100011011100110100100000011 #
b0111001001101111011000100110111101110100011011100110100100000011 +
b011 3
#12000
b0111001001101111011000100110111101110100011011100110100100000100 #
b0111001001101111011000100110111101110100011011100110100100000100 +
b100 3
#13000
b0111001001101111011000100110111101110100011011100110100100000101 #
b0111001001101111011000100110111101110100011011100110100100000101 +
b101 3
#14000
b0111001001101111011000100110111101110100011011100110100100000110 #
b0111001001101111011000100110111101110100011011100110100100000110 +
b110 3
#15000
b0111001001101111011000100110111101110100011011100110100100000111 #
b0111001001101111011000100110111101110100011011100110100100000111 +
b111 3
#16000
b0111001001101111011000100110111101110100011011100110100100000000 #
b1011111100110100001111000100011101000101101111101101100001101111 &
b11111111 (
b1011111100110100001111000100011101000101101111101101100001101111 )
b0111001001101111011000100110111101110100011011100110100100000000 +
b1011111100110100001111000100011101000101101111101101100001101111 .
b11111111 0
b1011111100110100001111000100011101000101101111101101100001101111 1
b000 3
#17000
b0111001001101111011000100110111101110100011011100110100100000001 #
b00000000 (
b0111001001101111011000100110111101110100011011100110100100000001 +
b00000000 0
b001 3
#18000
b0111001001101111011000100110111101110100011011100110100100000010 #
b0111001001101111011000100110111101110100011011100110100100000010 +
b010 3
#19000
b0111001001101111011000100110111101110100011011100110100100000011 #
b0111001001101111011000100110111101110100011011100110100100000011 +
b011 3
#20000
b0111001001101111011000100110111101110100011011100110100100000100 #
b0111001001101111011000100110111101110100011011100110100100000100 +
b100 3
#21000
b0111001001101111011000100110111101110100011011100110100100000101 #
b0111001001101111011000100110111101110100011011100110100100000101 +
b101 3
#22000
b0111001001101111011000100110111101110100011011100110100100000110 #
b0111001001101111011000100110111101110100011011100110100100000110 +
b110 3
#23000
b0111001001101111011000100110111101110100011011100110100100000111 #
b0111001001101111011000100110111101110100011011100110100100000111 +
b111 3
#24000
b0111001001101111011000100110111101110100011011100110100100000000 #
b1001110100111100011001100101000001100011001010001011111100111010 &
b11111111 (
b1001110100111100011001100101000001100011001010001011111100111010 )
b0111001001101111011000100110111101110100011011100110100100000000 +
b1001110100111100011001100101000001100011001010001011111100111010 .
b11111111 0
b1001110100111100011001100101000001100011001010001011111100111010 1
b000 3
#25000
b0111001001101111011000100110111101110100011011100110100100000001 #
b00000000 (
b0111001001101111011000100110111101110100011011100110100100000001 +
b00000000 0
b001 3
#26000
b0111001001101111011000100110111101110100011011100110100100000010 #
b0111001001101111011000100110111101110100011011100110100100000010 +
b010 3
#27000
b0111001001101111011000100110111101110100011011100110100100000011 #
b0111001001101111011000100110111101110100011011100110100100000011 +
b011 3
#28000
b0111001001101111011000100110111101110100011011100110100100000100 #
b0111001001101111011000100110111101110100011011100110100100000100 +
b100 3
#29000
b0111001001101111011000100110111101110100011011100110100100000101 #
b0111001001101111011000100110111101110100011011100110100100000101 +
b101 3
#30000
b0111001001101111011000100110111101110100011011100110100100000110 #
b0111001001101111011000100110111101110100011011100110100100000110 +
b110 3
#31000
b0111001001101111011000100110111101110100011011100110100100000111 #
b0111001001101111011000100110111101110100011011100110100100000111 +
b111 3
#32000
b0111001001101111011000100110111101110100011011100110100100000000 #
b0101000110111101111111010010000110101011101100111000011101010101 &
b11111111 (
b0101000110111101111111010010000110101011101100111000011101010101 )
b0111001001101111011000100110111101110100011011100110100100000000 +
b0101000110111101111111010010000110101011101100111000011101010101 .
b11111111 0
b0101000110111101111111010010000110101011101100111000011101010101 1
b000 3
#33000
b0111001001101111011000100110111101110100011011100110100100000001 #
b00000000 (
b0111001001101111011000100110111101110100011011100110100100000001 +
b00000000 0
b001 3
#34000
b0111001001101111011000100110111101110100011011100110100100000010 #
b0111001001101111011000100110111101110100011011100110100100000010 +
b010 3
#35000
b0111001001101111011000100110111101110100011011100110100100000011 #
b0111001001101111011000100110111101110100011011100110100100000011 +
b011 3
#36000
b0111001001101111011000100110111101110100011011100110100100000100 #
b0111001001101111011000100110111101110100011011100110100100000100 +
b100 3
#37000
b0111001001101111011000100110111101110100011011100110100100000101 #
b0111001001101111011000100110111101110100011011100110100100000101 +
b101 3
#38000
b0111001001101111011000100110111101110100011011100110100100000110 #
b0111001001101111011000100110111101110100011011100110100100000110 +
b110 3
#39000
b0111001001101111011000100110111101110100011011100110100100000111 #
b0111001001101111011000100110111101110100011011100110100100000111 +
b111 3
#40000
b0111001001101111011000100110111101110100011011100110100100000000 #
b1001111010100000010110100011101100110100111110101100010100010010 &
b11111111 (
b1001111010100000010110100011101100110100111110101100010100010010 )
b0111001001101111011000100110111101110100011011100110100100000000 +
b1001111010100000010110100011101100110100111110101100010100010010 .
b11111111 0
b1001111010100000010110100011101100110100111110101100010100010010 1
b000 3
#41000
b0111001001101111011000100110111101110100011011100110100100000001 #
b00000000 (
b0111001001101111011000100110111101110100011011100110100100000001 +
b00000000 0
b001 3
#42000
b0111001001101111011000100110111101110100011011100110100100000010 #
b0111001001101111011000100110111101110100011011100110100100000010 +
b010 3
#43000
b0111001001101111011000100110111101110100011011100110100100000011 #
b0111001001101111011000100110111101110100011011100110100100000011 +
b011 3
#44000
b0111001001101111011000100110111101110100011011100110100100000100 #
b0111001001101111011000100110111101110100011011100110100100000100 +
b100 3
#45000
b0111001001101111011000100110111101110100011011100110100100000101 #
b0111001001101111011000100110111101110100011011100110100100000101 +
b101 3
#46000
b0111001001101111011000100110111101110100011011100110100100000110 #
b0111001001101111011000100110111101110100011011100110100100000110 +
b110 3
#47000
b0111001001101111011000100110111101110100011011100110100100000111 #
b0111001001101111011000100110111101110100011011100110100100000111 +
b111 3
#48000
b0111001001101111011000100110111101110100011011100110100100000000 #
b0000011110100101100000100111101100110110100101100111011100111000 &
b11111111 (
b0000011110100101100000100111101100110110100101100111011100111000 )
b0111001001101111011000100110111101110100011011100110100100000000 +
b0000011110100101100000100111101100110110100101100111011100111000 .
b11111111 0
b0000011110100101100000100111101100110110100101100111011100111000 1
b000 3
#49000
b0111001001101111011000100110111101110100011011100110100100000001 #
b00000000 (
b0111001001101111011000100110111101110100011011100110100100000001 +
b00000000 0
b001 3
#50000
b0111001001101111011000100110111101110100011011100110100100000010 #
b0111001001101111011000100110111101110100011011100110100100000010 +
b010 3
#51000
b0111001001101111011000100110111101110100011011100110100100000011 #
b0111001001101111011000100110111101110100011011100110100100000011 +
b011 3
#52000
b0111001001101111011000100110111101110100011011100110100100000100 #
b0111001001101111011000100110111101110100011011100110100100000100 +
b100 3
#53000
b0111001001101111011000100110111101110100011011100110100100000101 #
b0111001001101111011000100110111101110100011011100110100100000101 +
b101 3
#54000
b0111001001101111011000100110111101110100011011100110100100000110 #
b0111001001101111011000100110111101110100011011100110100100000110 +
b110 3
#55000
b0111001001101111011000100110111101110100011011100110100100000111 #
b0111001001101111011000100110111101110100011011100110100100000111 +
b111 3
#56000
b0111001001101111011000100110111101110100011011100110100100000000 #
b1010110001000111111011110000100011011100000111111100000100111110 &
b11111111 (
b1010110001000111111011110000100011011100000111111100000100111110 )
b0111001001101111011000100110111101110100011011100110100100000000 +
b1010110001000111111011110000100011011100000111111100000100111110 .
b11111111 0
b1010110001000111111011110000100011011100000111111100000100111110 1
b000 3
#57000
b0111001001101111011000100110111101110100011011100110100100000001 #
b00000000 (
b0111001001101111011000100110111101110100011011100110100100000001 +
b00000000 0
b001 3
#58000
b0111001001101111011000100110111101110100011011100110100100000010 #
b0111001001101111011000100110111101110100011011100110100100000010 +
b010 3
#59000
b0111001001101111011000100110111101110100011011100110100100000011 #
b0111001001101111011000100110111101110100011011100110100100000011 +
b011 3
#60000
b0111001001101111011000100110111101110100011011100110100100000100 #
b0111001001101111011000100110111101110100011011100110100100000100 +
b100 3
#61000
b0111001001101111011000100110111101110100011011100110100100000101 #
b0111001001101111011000100110111101110100011011100110100100000101 +
b101 3
#62000
b0111001001101111011000100110111101110100011011100110100100000110 #
b0111001001101111011000100110111101110100011011100110100100000110 +
b110 3
#63000
b0111001001101111011000100110111101110100011011100110100100000111 #
b0111001001101111011000100110111101110100011011100110100100000111 +
b111 3
#64000
b0111001001101111011000100110111101110100011011100110100100000000 #
b1100111101000001100011000001010110010101001000101000001101010101 &
b11111111 (
b1100111101000001100011000001010110010101001000101000001101010101 )
b0111001001101111011000100110111101110100011011100110100100000000 +
b1100111101000001100011000001010110010101001000101000001101010101 .
b11111111 0
b1100111101000001100011000001010110010101001000101000001101010101 1
b000 3
#65000
b0111001001101111011000100110111101110100011011100110100100000001 #
b00000000 (
b0111001001101111011000100110111101110100011011100110100100000001 +
b00000000 0
b001 3
#66000
b0111001001101111011000100110111101110100011011100110100100000010 #
b0111001001101111011000100110111101110100011011100110100100000010 +
b010 3
#67000
b0111001001101111011000100110111101110100011011100110100100000011 #
b0111001001101111011000100110111101110100011011100110100100000011 +
b011 3
#68000
b0111001001101111011000100110111101110100011011100110100100000100 #
b0111001001101111011000100110111101110100011011100110100100000100 +
b100 3
#69000
b0111001001101111011000100110111101110100011011100110100100000101 #
b0111001001101111011000100110111101110100011011100110100100000101 +
b101 3
#70000
b0111001001101111011000100110111101110100011011100110100100000110 #
b0111001001101111011000100110111101110100011011100110100100000110 +
b110 3
#71000
b0111001001101111011000100110111101110100011011100110100100000111 #
b0111001001101111011000100110111101110100011011100110100100000111 +
b111 3
#72000
b0111001001101111011000100110111101110100011011100110100100000000 #
b0101001000110101100111111011110000000010110101101110111010100001 &
b11111111 (
b0101001000110101100111111011110000000010110101101110111010100001 )
b0111001001101111011000100110111101110100011011100110100100000000 +
b0101001000110101100111111011110000000010110101101110111010100001 .
b11111111 0
b0101001000110101100111111011110000000010110101101110111010100001 1
b000 3
#73000
b0111001001101111011000100110111101110100011011100110100100000001 #
b00000000 (
b0111001001101111011000100110111101110100011011100110100100000001 +
b00000000 0
b001 3
#74000
b0111001001101111011000100110111101110100011011100110100100000010 #
b0111001001101111011000100110111101110100011011100110100100000010 +
b010 3
#75000
b0111001001101111011000100110111101110100011011100110100100000011 #
b0111001001101111011000100110111101110100011011100110100100000011 +
b011 3
#76000
b0111001001101111011000100110111101110100011011100110100100000100 #
b0111001001101111011000100110111101110100011011100110100100000100 +
b100 3
#77000
b0111001001101111011000100110111101110100011011100110100100000101 #
b0111001001101111011000100110111101110100011011100110100100000101 +
b101 3
#78000
b0111001001101111011000100110111101110100011011100110100100000110 #
b0111001001101111011000100110111101110100011011100110100100000110 +
b110 3
#79000
b0111001001101111011000100110111101110100011011100110100100000111 #
b0111001001101111011000100110111101110100011011100110100100000111 +
b111 3
#80000
b0111001001101111011000100110111101110100011011100110100100000000 #
b0101000110000100000001001110010010001000100010101111011110111111 &
b11111111 (
b0101000110000100000001001110010010001000100010101111011110111111 )
b0111001001101111011000100110111101110100011011100110100100000000 +
b0101000110000100000001001110010010001000100010101111011110111111 .
b11111111 0
b0101000110000100000001001110010010001000100010101111011110111111 1
b000 3
#81000
b0111001001101111011000100110111101110100011011100110100100000001 #
b00000000 (
b0111001001101111011000100110111101110100011011100110100100000001 +
b00000000 0
b001 3
#82000
b0111001001101111011000100110111101110100011011100110100100000010 #
b0111001001101111011000100110111101110100011011100110100100000010 +
b010 3
#83000
b0111001001101111011000100110111101110100011011100110100100000011 #
b0111001001101111011000100110111101110100011011100110100100000011 +
b011 3
#84000
b0111001001101111011000100110111101110100011011100110100100000100 #
b0111001001101111011000100110111101110100011011100110100100000100 +
b100 3
#85000
b0111001001101111011000100110111101110100011011100110100100000101 #
b0111001001101111011000100110111101110100011011100110100100000101 +
b101 3
#86000
b0111001001101111011000100110111101110100011011100110100100000110 #
b0111001001101111011000100110111101110100011011100110100100000110 +
b110 3
#87000
b0111001001101111011000100110111101110100011011100110100100000111 #
b0111001001101111011000100110111101110100011011100110100100000111 +
b111 3
#88000
b0111001001101111011000100110111101110100011011100110100100000000 #
b1000110101000100010000011100010000110100010100001010110111011110 &
b11111111 (
b1000110101000100010000011100010000110100010100001010110111011110 )
b0111001001101111011000100110111101110100011011100110100100000000 +
b1000110101000100010000011100010000110100010100001010110111011110 .
b11111111 0
b1000110101000100010000011100010000110100010100001010110111011110 1
b000 3
#89000
b0111001001101111011000100110111101110100011011100110100100000001 #
b00000000 (
b0111001001101111011000100110111101110100011011100110100100000001 +
b00000000 0
b001 3
#90000
b0111001001101111011000100110111101110100011011100110100100000010 #
b0111001001101111011000100110111101110100011011100110100100000010 +
b010 3
#91000
b0111001001101111011000100110111101110100011011100110100100000011 #
b0111001001101111011000100110111101110100011011100110100100000011 +
b011 3
#92000
b0111001001101111011000100110111101110100011011100110100100000100 #
b0111001001101111011000100110111101110100011011100110100100000100 +
b100 3
#93000
b0111001001101111011000100110111101110100011011100110100100000101 #
b0111001001101111011000100110111101110100011011100110100100000101 +
b101 3
#94000
b0111001001101111011000100110111101110100011011100110100100000110 #
b0111001001101111011000100110111101110100011011100110100100000110 +
b110 3
#95000
b0111001001101111011000100110111101110100011011100110100100000111 #
b0111001001101111011000100110111101110100011011100110100100000111 +
b111 3
#96000
b0111001001101111011000100110111101110100011011100110100100000000 #
b1010001110011111101110001001101110001000011001101001011110101111 &
b11111111 (
b1010001110011111101110001001101110001000011001101001011110101111 )
b0111001001101111011000100110111101110100011011100110100100000000 +
b1010001110011111101110001001101110001000011001101001011110101111 .
b11111111 0
b1010001110011111101110001001101110001000011001101001011110101111 1
b000 3
#97000
b0111001001101111011000100110111101110100011011100110100100000001 #
b00000000 (
b0111001001101111011000100110111101110100011011100110100100000001 +
b00000000 0
b001 3
#98000
b0111001001101111011000100110111101110100011011100110100100000010 #
b0111001001101111011000100110111101110100011011100110100100000010 +
b010 3
#99000
b0111001001101111011000100110111101110100011011100110100100000011 #
b0111001001101111011000100110111101110100011011100110100100000011 +
b011 3
#100000
b0111001001101111011000100110111101110100011011100110100100000100 #
b0111001001101111011000100110111101110100011011100110100100000100 +
b100 3
#101000
b0111001001101111011000100110111101110100011011100110100100000101 #
b0111001001101111011000100110111101110100011011100110100100000101 +
b101 3
#102000
b0111001001101111011000100110111101110100011011100110100100000110 #
b0111001001101111011000100110111101110100011011100110100100000110 +
b110 3
#103000
b0111001001101111011000100110111101110100011011100110100100000111 #
b0111001001101111011000100110111101110100011011100110100100000111 +
b111 3
#104000
b0111001001101111011000100110111101110100011011100110100100000000 #
b0100011011011001010110111110001101100110101111100111111001001110 &
b11111111 (
b0100011011011001010110111110001101100110101111100111111001001110 )
b0111001001101111011000100110111101110100011011100110100100000000 +
b0100011011011001010110111110001101100110101111100111111001001110 .
b11111111 0
b0100011011011001010110111110001101100110101111100111111001001110 1
b000 3
#105000
b0111001001101111011000100110111101110100011011100110100100000001 #
b00000000 (
b0111001001101111011000100110111101110100011011100110100100000001 +
b00000000 0
b001 3
#106000
b0111001001101111011000100110111101110100011011100110100100000010 #
b0111001001101111011000100110111101110100011011100110100100000010 +
b010 3
#107000
b0111001001101111011000100110111101110100011011100110100100000011 #
b0111001001101111011000100110111101110100011011100110100100000011 +
b011 3
#108000
b0111001001101111011000100110111101110100011011100110100100000100 #
b0111001001101111011000100110111101110100011011100110100100000100 +
b100 3
#109000
b0111001001101111011000100110111101110100011011100110100100000101 #
b0111001001101111011000100110111101110100011011100110100100000101 +
b101 3
#110000
b0111001001101111011000100110111101110100011011100110100100000110 #
b0111001001101111011000100110111101110100011011100110100100000110 +
b110 3
#111000
b0111001001101111011000100110111101110100011011100110100100000111 #
b0111001001101111011000100110111101110100011011100110100100000111 +
b111 3
#112000
b0111001001101111011000100110111101110100011011100110100100000000 #
b1100010010000011001011100100010011111111001000100010010010011011 &
b11111111 (
b1100010010000011001011100100010011111111001000100010010010011011 )
b0111001001101111011000100110111101110100011011100110100100000000 +
b1100010010000011001011100100010011111111001000100010010010011011 .
b11111111 0
b1100010010000011001011100100010011111111001000100010010010011011 1
b000 3
#113000
b0111001001101111011000100110111101110100011011100110100100000001 #
b00000000 (
b0111001001101111011000100110111101110100011011100110100100000001 +
b00000000 0
b001 3
#114000
b0111001001101111011000100110111101110100011011100110100100000010 #
b0111001001101111011000100110111101110100011011100110100100000010 +
b010 3
#115000
b0111001001101111011000100110111101110100011011100110100100000011 #
b0111001001101111011000100110111101110100011011100110100100000011 +
b011 3
#116000
b0111001001101111011000100110111101110100011011100110100100000100 #
b0111001001101111011000100110111101110100011011100110100100000100 +
b100 3
#117000
b0111001001101111011000100110111101110100011011100110100100000101 #
b0111001001101111011000100110111101110100011011100110100100000101 +
b101 3
#118000
b0111001001101111011000100110111101110100011011100110100100000110 #
b0111001001101111011000100110111101110100011011100110100100000110 +
b110 3
#119000
b0111001001101111011000100110111101110100011011100110100100000111 #
b0111001001101111011000100110111101110100011011100110100100000111 +
b111 3
#120000
b0111001001101111011000100110111101110100011011100110100100000000 #
b1011011111011101001001010001111101100000100000011111111100100001 &
b11111111 (
b1011011111011101001001010001111101100000100000011111111100100001 )
b0111001001101111011000100110111101110100011011100110100100000000 +
b1011011111011101001001010001111101100000100000011111111100100001 .
b11111111 0
b1011011111011101001001010001111101100000100000011111111100100001 1
b000 3
#121000
b0111001001101111011000100110111101110100011011100110100100000001 #
b00000000 (
b0111001001101111011000100110111101110100011011100110100100000001 +
b00000000 0
b001 3
#122000
b0111001001101111011000100110111101110100011011100110100100000010 #
b0111001001101111011000100110111101110100011011100110100100000010 +
b010 3
#123000
b0111001001101111011000100110111101110100011011100110100100000011 #
b0111001001101111011000100110111101110100011011100110100100000011 +
b011 3
#124000
b0111001001101111011000100110111101110100011011100110100100000100 #
b0111001001101111011000100110111101110100011011100110100100000100 +
b100 3
#125000
b0111001001101111011000100110111101110100011011100110100100000101 #
b0111001001101111011000100110111101110100011011100110100100000101 +
b101 3
#126000
b0111001001101111011000100110111101110100011011100110100100000110 #
b0111001001101111011000100110111101110100011011100110100100000110 +
b110 3
#127000
b0111001001101111011000100110111101110100011011100110100100000111 #
b0111001001101111011000100110111101110100011011100110100100000111 +
b111 3
#128000
b0111001001101111011000100110111101110100011011100110100100000000 #
b1001001010000101110110100100100010011011011000011100011101000010 &
b11111111 (
b1001001010000101110110100100100010011011011000011100011101000010 )
b0111001001101111011000100110111101110100011011100110100100000000 +
b1001001010000101110110100100100010011011011000011100011101000010 .
b11111111 0
b1001001010000101110110100100100010011011011000011100011101000010 1
b000 3
#129000
b0111001001101111011000100110111101110100011011100110100100000001 #
b00000000 (
b0111001001101111011000100110111101110100011011100110100100000001 +
b00000000 0
b001 3
#130000
b0111001001101111011000100110111101110100011011100110100100000010 #
b0111001001101111011000100110111101110100011011100110100100000010 +
b010 3
#131000
b0111001001101111011000100110111101110100011011100110100100000011 #
b0111001001101111011000100110111101110100011011100110100100000011 +
b011 3
#132000
b0111001001101111011000100110111101110100011011100110100100000100 #
b0111001001101111011000100110111101110100011011100110100100000100 +
b100 3
#133000
b0111001001101111011000100110111101110100011011100110100100000101 #
b0111001001101111011000100110111101110100011011100110100100000101 +
b101 3
#134000
b0111001001101111011000100110111101110100011011100110100100000110 #
b0111001001101111011000100110111101110100011011100110100100000110 +
b110 3
#135000
b0111001001101111011000100110111101110100011011100110100100000111 #
b0111001001101111011000100110111101110100011011100110100100000111 +
b111 3
#136000
b0111001001101111011000100110111101110100011011100110100100000000 #
b0101000110111011101110011011010011111110001000011100000101001111 &
b11111111 (
b0101000110111011101110011011010011111110001000011100000101001111 )
b0111001001101111011000100110111101110100011011100110100100000000 +
b0101000110111011101110011011010011111110001000011100000101001111 .
b11111111 0
b0101000110111011101110011011010011111110001000011100000101001111 1
b000 3
#137000
b0111001001101111011000100110111101110100011011100110100100000001 #
b00000000 (
b0111001001101111011000100110111101110100011011100110100100000001 +
b00000000 0
b001 3
#138000
b0111001001101111011000100110111101110100011011100110100100000010 #
b0111001001101111011000100110111101110100011011100110100100000010 +
b010 3
#139000
b0111001001101111011000100110111101110100011011100110100100000011 #
b0111001001101111011000100110111101110100011011100110100100000011 +
b011 3
#140000
b0111001001101111011000100110111101110100011011100110100100000100 #
b0111001001101111011000100110111101110100011011100110100100000100 +
b100 3
#141000
b0111001001101111011000100110111101110100011011100110100100000101 #
b0111001001101111011000100110111101110100011011100110100100000101 +
b101 3
#142000
b0111001001101111011000100110111101110100011011100110100100000110 #
b0111001001101111011000100110111101110100011011100110100100000110 +
b110 3
#143000
b0111001001101111011000100110111101110100011011100110100100000111 #
b0111001001101111011000100110111101110100011011100110100100000111 +
b111 3
#144000
b0111001001101111011000100110111101110100011011100110100100000000 #
b1110100110001110100100001010000111111101111000011111100101110010 &
b11111111 (
b1110100110001110100100001010000111111101111000011111100101110010 )
b0111001001101111011000100110111101110100011011100110100100000000 +
b1110100110001110100100001010000111111101111000011111100101110010 .
b11111111 0
b1110100110001110100100001010000111111101111000011111100101110010 1
b000 3
#145000
b0111001001101111011000100110111101110100011011100110100100000001 #
b00000000 (
b0111001001101111011000100110111101110100011011100110100100000001 +
b00000000 0
b001 3
#146000
b0111001001101111011000100110111101110100011011100110100100000010 #
b0111001001101111011000100110111101110100011011100110100100000010 +
b010 3
#147000
b0111001001101111011000100110111101110100011011100110100100000011 #
b0111001001101111011000100110111101110100011011100110100100000011 +
b011 3
#148000
b0111001001101111011000100110111101110100011011100110100100000100 #
b0111001001101111011000100110111101110100011011100110100100000100 +
b100 3
#149000
b0111001001101111011000100110111101110100011011100110100100000101 #
b0111001001101111011000100110111101110100011011100110100100000101 +
b101 3
#150000
b0111001001101111011000100110111101110100011011100110100100000110 #
b0111001001101111011000100110111101110100011011100110100100000110 +
b110 3
#151000
b0111001001101111011000100110111101110100011011100110100100000111 #
b0111001001101111011000100110111101110100011011100110100100000111 +
b111 3
#152000
b0111001001101111011000100110111101110100011011100110100100000000 #
b1101101100100010101000110110111010110010111111011110011000011001 &
b11111111 (
b1101101100100010101000110110111010110010111111011110011000011001 )
b0111001001101111011000100110111101110100011011100110100100000000 +
b1101101100100010101000110110111010110010111111011110011000011001 .
b11111111 0
b1101101100100010101000110110111010110010111111011110011000011001 1
b000 3
#153000
b0111001001101111011000100110111101110100011011100110100100000001 #
b00000000 (
b0111001001101111011000100110111101110100011011100110100100000001 +
b00000000 0
b001 3
#154000
b0111001001101111011000100110111101110100011011100110100100000010 #
b0111001001101111011000100110111101110100011011100110100100000010 +
b010 3
#155000
b0111001001101111011000100110111101110100011011100110100100000011 #
b0111001001101111011000100110111101110100011011100110100100000011 +
b011 3
#156000
b0111001001101111011000100110111101110100011011100110100100000100 #
b0111001001101111011000100110111101110100011011100110100100000100 +
b100 3
#157000
b0111001001101111011000100110111101110100011011100110100100000101 #
b0111001001101111011000100110111101110100011011100110100100000101 +
b101 3
#158000
b0111001001101111011000100110111101110100011011100110100100000110 #
b0111001001101111011000100110111101110100011011100110100100000110 +
b110 3
#159000
b0111001001101111011000100110111101110100011011100110100100000111 #
b0111001001101111011000100110111101110100011011100110100100000111 +
b111 3
#160000
b0111001001101111011000100110111101110100011011100110100100000000 #
b1111101101111001101111101001111000110011111110001010111011000101 &
b11111111 (
b1111101101111001101111101001111000110011111110001010111011000101 )
b0111001001101111011000100110111101110100011011100110100100000000 +
b1111101101111001101111101001111000110011111110001010111011000101 .
b11111111 0
b1111101101111001101111101001111000110011111110001010111011000101 1
b000 3
#161000
b0111001001101111011000100110111101110100011011100110100100000001 #
b00000000 (
b0111001001101111011000100110111101110100011011100110100100000001 +
b00000000 0
b001 3
#162000
b0111001001101111011000100110111101110100011011100110100100000010 #
b0111001001101111011000100110111101110100011011100110100100000010 +
b010 3
#163000
b0111001001101111011000100110111101110100011011100110100100000011 #
b0111001001101111011000100110111101110100011011100110100100000011 +
b011 3
#164000
b0111001001101111011000100110111101110100011011100110100100000100 #
b0111001001101111011000100110111101110100011011100110100100000100 +
b100 3
#165000
b0111001001101111011000100110111101110100011011100110100100000101 #
b0111001001101111011000100110111101110100011011100110100100000101 +
b101 3
#166000
b0111001001101111011000100110111101110100011011100110100100000110 #
b0111001001101111011000100110111101110100011011100110100100000110 +
b110 3
#167000
b0111001001101111011000100110111101110100011011100110100100000111 #
b0111001001101111011000100110111101110100011011100110100100000111 +
b111 3
#168000
b0111001001101111011000100110111101110100011011100110100100000000 #
b1101110111000101011010101010011000000111011101010100000001010100 &
b11111111 (
b1101110111000101011010101010011000000111011101010100000001010100 )
b0111001001101111011000100110111101110100011011100110100100000000 +
b1101110111000101011010101010011000000111011101010100000001010100 .
b11111111 0
b1101110111000101011010101010011000000111011101010100000001010100 1
b000 3
#169000
b0111001001101111011000100110111101110100011011100110100100000001 #
b00000000 (
b0111001001101111011000100110111101110100011011100110100100000001 +
b00000000 0
b001 3
#170000
b0111001001101111011000100110111101110100011011100110100100000010 #
b0111001001101111011000100110111101110100011011100110100100000010 +
b010 3
